Workbook

Sheet 값
B1: 사모벤처 | L1: 부동산 | R1: 인프라
B2: Buyout | C2: Growth | D2: Venture Capital | E2: Fund of Fund | F2: Long-term Core | G2: GP-Stake / Continuation Vehicle | H2: Senior Credit | I2: Junior Credit | J2: 국내 사모투자 | K2: Hedge Fund | L2: Core RE Equity | M2: Non-Core RE Equity | N2: 국내 부동산 | O2: Core RE Debt | P2: Non-Core RE Debt | Q2: Listed RE | R2: Core 국내 인프라 | S2: Non-Core 국내 인프라 | T2: Core 해외 인프라 | U2: Non-Core 해외 인프라 | V2: Super-Core Infrastructure
A3: 날짜 | B3: Burgiss Buyout Index | C3: Burgiss Venture Capital Index | D3: Burgiss Venture Capital Index | E3: Burgiss FoF Secondary Equity Index | F3: Burgiss FoF Primary Equity Index | G3: Burgiss FoF Secondary Equity Index | H3: Burgiss Senior Loan Index | I3: Burgiss Mezzanine Index | J3: Burgiss Equity Index (Asia & Pacific) | K3: HFRI FoF: Conservative Index | L3: MSCI Global Property Fund Index | M3: Burgiss Real Estate Equity Index (value-add, Opportunistic) | N3: MSCI Global Property Fund Index | O3: Giliberto-Levy Commercial Mortgage Performance Index (G-L 1) | P3: Giliberto-Levy High-Yield Real Estate Debt Index (G-L 2) | Q3: FTSE EPRA/NAREIT Developed Index | R3: Burgiss Infrastructure Equity Index (Core) | S3: Burgiss Infrastructure Equity Index (Core) | T3: Burgiss Infrastructure Equity Index (Core) | U3: Burgiss Infrastructure Equity Index (Core) | V3: FTSE Fixed Income Core Infrastrue Index
A4: 36616 | B4: =VLOOKUP($A4,[1]Burgiss_Return!$B:$P,MATCH(B$2,[1]Burgiss_Return!$B$5:$P$5,0),0) -> 0.1103 | C4: =VLOOKUP($A4,[1]Burgiss_Return!$B:$P,MATCH(C$2,[1]Burgiss_Return!$B$5:$P$5,0),0) -> 0.1533 | D4: =VLOOKUP($A4,[1]Burgiss_Return!$B:$P,MATCH(D$2,[1]Burgiss_Return!$B$5:$P$5,0),0) -> 0.1533 | F4: =VLOOKUP($A4,[1]Burgiss_Return!$B:$P,MATCH(F$2,[1]Burgiss_Return!$B$5:$P$5,0),0) -> 0.0053 | I4: =VLOOKUP($A4,[1]Burgiss_Return!$B:$P,MATCH(I$2,[1]Burgiss_Return!$B$5:$P$5,0),0) -> 0.0114 | J4: =VLOOKUP($A4,[1]Burgiss_Return!$B:$P,MATCH(J$2,[1]Burgiss_Return!$B$5:$P$5,0),0) -> 0.0383 | K4: 0.048656061 | M4: =VLOOKUP($A4,[1]Burgiss_Return!$B:$P,MATCH(M$2,[1]Burgiss_Return!$B$5:$P$5,0),0) -> 0.0334 | Q4: -0.0248
A5: 36707 | B5: =VLOOKUP($A5,[1]Burgiss_Return!$B:$P,MATCH(B$2,[1]Burgiss_Return!$B$5:$P$5,0),0) -> -0.0009 | C5: =VLOOKUP($A5,[1]Burgiss_Return!$B:$P,MATCH(C$2,[1]Burgiss_Return!$B$5:$P$5,0),0) -> 0.0751 | D5: =VLOOKUP($A5,[1]Burgiss_Return!$B:$P,MATCH(D$2,[1]Burgiss_Return!$B$5:$P$5,0),0) -> 0.0751 | F5: =VLOOKUP($A5,[1]Burgiss_Return!$B:$P,MATCH(F$2,[1]Burgiss_Return!$B$5:$P$5,0),0) -> 0.0363 | I5: =VLOOKUP($A5,[1]Burgiss_Return!$B:$P,MATCH(I$2,[1]Burgiss_Return!$B$5:$P$5,0),0) -> 0.0159 | J5: =VLOOKUP($A5,[1]Burgiss_Return!$B:$P,MATCH(J$2,[1]Burgiss_Return!$B$5:$P$5,0),0) -> -0.0852 | K5: -0.0055559234 | M5: =VLOOKUP($A5,[1]Burgiss_Return!$B:$P,MATCH(M$2,[1]Burgiss_Return!$B$5:$P$5,0),0) -> 0.0566 | Q5: 0.03609516
A6: 36799 | B6: =VLOOKUP($A6,[1]Burgiss_Return!$B:$P,MATCH(B$2,[1]Burgiss_Return!$B$5:$P$5,0),0) -> -0.0295 | C6: =VLOOKUP($A6,[1]Burgiss_Return!$B:$P,MATCH(C$2,[1]Burgiss_Return!$B$5:$P$5,0),0) -> 0.1497 | D6: =VLOOKUP($A6,[1]Burgiss_Return!$B:$P,MATCH(D$2,[1]Burgiss_Return!$B$5:$P$5,0),0) -> 0.1497 | F6: =VLOOKUP($A6,[1]Burgiss_Return!$B:$P,MATCH(F$2,[1]Burgiss_Return!$B$5:$P$5,0),0) -> 0.0089 | I6: =VLOOKUP($A6,[1]Burgiss_Return!$B:$P,MATCH(I$2,[1]Burgiss_Return!$B$5:$P$5,0),0) -> 0.0368 | J6: =VLOOKUP($A6,[1]Burgiss_Return!$B:$P,MATCH(J$2,[1]Burgiss_Return!$B$5:$P$5,0),0) -> -0.0453 | K6: 0.0085359625 | M6: =VLOOKUP($A6,[1]Burgiss_Return!$B:$P,MATCH(M$2,[1]Burgiss_Return!$B$5:$P$5,0),0) -> 0.0114 | Q6: 0.074871338
A7: 36891 | B7: =VLOOKUP($A7,[1]Burgiss_Return!$B:$P,MATCH(B$2,[1]Burgiss_Return!$B$5:$P$5,0),0) -> -0.0306 | C7: =VLOOKUP($A7,[1]Burgiss_Return!$B:$P,MATCH(C$2,[1]Burgiss_Return!$B$5:$P$5,0),0) -> -0.1013 | D7: =VLOOKUP($A7,[1]Burgiss_Return!$B:$P,MATCH(D$2,[1]Burgiss_Return!$B$5:$P$5,0),0) -> -0.1013 | F7: =VLOOKUP($A7,[1]Burgiss_Return!$B:$P,MATCH(F$2,[1]Burgiss_Return!$B$5:$P$5,0),0) -> -0.0575 | I7: =VLOOKUP($A7,[1]Burgiss_Return!$B:$P,MATCH(I$2,[1]Burgiss_Return!$B$5:$P$5,0),0) -> -0.0183 | J7: =VLOOKUP($A7,[1]Burgiss_Return!$B:$P,MATCH(J$2,[1]Burgiss_Return!$B$5:$P$5,0),0) -> -0.0729 | K7: 0.0056814788 | M7: =VLOOKUP($A7,[1]Burgiss_Return!$B:$P,MATCH(M$2,[1]Burgiss_Return!$B$5:$P$5,0),0) -> 0.0666 | Q7: 0.048211408
A8: 36981 | B8: =VLOOKUP($A8,[1]Burgiss_Return!$B:$P,MATCH(B$2,[1]Burgiss_Return!$B$5:$P$5,0),0) -> -0.0635 | C8: =VLOOKUP($A8,[1]Burgiss_Return!$B:$P,MATCH(C$2,[1]Burgiss_Return!$B$5:$P$5,0),0) -> -0.0899 | D8: =VLOOKUP($A8,[1]Burgiss_Return!$B:$P,MATCH(D$2,[1]Burgiss_Return!$B$5:$P$5,0),0) -> -0.0899 | F8: =VLOOKUP($A8,[1]Burgiss_Return!$B:$P,MATCH(F$2,[1]Burgiss_Return!$B$5:$P$5,0),0) -> -0.0119 | I8: =VLOOKUP($A8,[1]Burgiss_Return!$B:$P,MATCH(I$2,[1]Burgiss_Return!$B$5:$P$5,0),0) -> 0.0647 | J8: =VLOOKUP($A8,[1]Burgiss_Return!$B:$P,MATCH(J$2,[1]Burgiss_Return!$B$5:$P$5,0),0) -> 0.0091 | K8: 0.0019250338 | M8: =VLOOKUP($A8,[1]Burgiss_Return!$B:$P,MATCH(M$2,[1]Burgiss_Return!$B$5:$P$5,0),0) -> 0.0312 | Q8: -0.050465122
A9: 37072 | B9: =VLOOKUP($A9,[1]Burgiss_Return!$B:$P,MATCH(B$2,[1]Burgiss_Return!$B$5:$P$5,0),0) -> 0.0238 | C9: =VLOOKUP($A9,[1]Burgiss_Return!$B:$P,MATCH(C$2,[1]Burgiss_Return!$B$5:$P$5,0),0) -> -0.0746 | D9: =VLOOKUP($A9,[1]Burgiss_Return!$B:$P,MATCH(D$2,[1]Burgiss_Return!$B$5:$P$5,0),0) -> -0.0746 | F9: =VLOOKUP($A9,[1]Burgiss_Return!$B:$P,MATCH(F$2,[1]Burgiss_Return!$B$5:$P$5,0),0) -> -0.0608 | I9: =VLOOKUP($A9,[1]Burgiss_Return!$B:$P,MATCH(I$2,[1]Burgiss_Return!$B$5:$P$5,0),0) -> 0.029 | J9: =VLOOKUP($A9,[1]Burgiss_Return!$B:$P,MATCH(J$2,[1]Burgiss_Return!$B$5:$P$5,0),0) -> -0.013 | K9: 0.015350924 | M9: =VLOOKUP($A9,[1]Burgiss_Return!$B:$P,MATCH(M$2,[1]Burgiss_Return!$B$5:$P$5,0),0) -> 0.0007 | Q9: 0.060150237
A10: 37164 | B10: =VLOOKUP($A10,[1]Burgiss_Return!$B:$P,MATCH(B$2,[1]Burgiss_Return!$B$5:$P$5,0),0) -> -0.0809 | C10: =VLOOKUP($A10,[1]Burgiss_Return!$B:$P,MATCH(C$2,[1]Burgiss_Return!$B$5:$P$5,0),0) -> -0.1505 | D10: =VLOOKUP($A10,[1]Burgiss_Return!$B:$P,MATCH(D$2,[1]Burgiss_Return!$B$5:$P$5,0),0) -> -0.1505 | F10: =VLOOKUP($A10,[1]Burgiss_Return!$B:$P,MATCH(F$2,[1]Burgiss_Return!$B$5:$P$5,0),0) -> -0.0545 | I10: =VLOOKUP($A10,[1]Burgiss_Return!$B:$P,MATCH(I$2,[1]Burgiss_Return!$B$5:$P$5,0),0) -> 0.0149 | J10: =VLOOKUP($A10,[1]Burgiss_Return!$B:$P,MATCH(J$2,[1]Burgiss_Return!$B$5:$P$5,0),0) -> -0.0254 | K10: -0.0009217345 | M10: =VLOOKUP($A10,[1]Burgiss_Return!$B:$P,MATCH(M$2,[1]Burgiss_Return!$B$5:$P$5,0),0) -> -0.0062 | Q10: -0.098300145
A11: 37256 | B11: =VLOOKUP($A11,[1]Burgiss_Return!$B:$P,MATCH(B$2,[1]Burgiss_Return!$B$5:$P$5,0),0) -> -0.0011 | C11: =VLOOKUP($A11,[1]Burgiss_Return!$B:$P,MATCH(C$2,[1]Burgiss_Return!$B$5:$P$5,0),0) -> -0.0779 | D11: =VLOOKUP($A11,[1]Burgiss_Return!$B:$P,MATCH(D$2,[1]Burgiss_Return!$B$5:$P$5,0),0) -> -0.0779 | F11: =VLOOKUP($A11,[1]Burgiss_Return!$B:$P,MATCH(F$2,[1]Burgiss_Return!$B$5:$P$5,0),0) -> -0.0812 | I11: =VLOOKUP($A11,[1]Burgiss_Return!$B:$P,MATCH(I$2,[1]Burgiss_Return!$B$5:$P$5,0),0) -> 0.021 | J11: =VLOOKUP($A11,[1]Burgiss_Return!$B:$P,MATCH(J$2,[1]Burgiss_Return!$B$5:$P$5,0),0) -> -0.0637 | K11: 0.014464422 | M11: =VLOOKUP($A11,[1]Burgiss_Return!$B:$P,MATCH(M$2,[1]Burgiss_Return!$B$5:$P$5,0),0) -> 0.0367 | Q11: 0.059738902
A12: 37346 | B12: =VLOOKUP($A12,[1]Burgiss_Return!$B:$P,MATCH(B$2,[1]Burgiss_Return!$B$5:$P$5,0),0) -> -0.0023 | C12: =VLOOKUP($A12,[1]Burgiss_Return!$B:$P,MATCH(C$2,[1]Burgiss_Return!$B$5:$P$5,0),0) -> -0.0948 | D12: =VLOOKUP($A12,[1]Burgiss_Return!$B:$P,MATCH(D$2,[1]Burgiss_Return!$B$5:$P$5,0),0) -> -0.0948 | E12: =VLOOKUP($A12,[1]Burgiss_Return!$B:$P,MATCH(E$2,[1]Burgiss_Return!$B$5:$P$5,0),0) -> 0.0327 | F12: =VLOOKUP($A12,[1]Burgiss_Return!$B:$P,MATCH(F$2,[1]Burgiss_Return!$B$5:$P$5,0),0) -> -0.025 | G12: =VLOOKUP($A12,[1]Burgiss_Return!$B:$P,MATCH(G$2,[1]Burgiss_Return!$B$5:$P$5,0),0) -> 0.0327 | I12: =VLOOKUP($A12,[1]Burgiss_Return!$B:$P,MATCH(I$2,[1]Burgiss_Return!$B$5:$P$5,0),0) -> 0.0377 | J12: =VLOOKUP($A12,[1]Burgiss_Return!$B:$P,MATCH(J$2,[1]Burgiss_Return!$B$5:$P$5,0),0) -> 0.0141 | K12: 0.013385806 | M12: =VLOOKUP($A12,[1]Burgiss_Return!$B:$P,MATCH(M$2,[1]Burgiss_Return!$B$5:$P$5,0),0) -> 0.0143 | Q12: 0.053759611
A13: 37437 | B13: =VLOOKUP($A13,[1]Burgiss_Return!$B:$P,MATCH(B$2,[1]Burgiss_Return!$B$5:$P$5,0),0) -> -0.0135 | C13: =VLOOKUP($A13,[1]Burgiss_Return!$B:$P,MATCH(C$2,[1]Burgiss_Return!$B$5:$P$5,0),0) -> -0.1303 | D13: =VLOOKUP($A13,[1]Burgiss_Return!$B:$P,MATCH(D$2,[1]Burgiss_Return!$B$5:$P$5,0),0) -> -0.1303 | E13: =VLOOKUP($A13,[1]Burgiss_Return!$B:$P,MATCH(E$2,[1]Burgiss_Return!$B$5:$P$5,0),0) -> 0.0174 | F13: =VLOOKUP($A13,[1]Burgiss_Return!$B:$P,MATCH(F$2,[1]Burgiss_Return!$B$5:$P$5,0),0) -> -0.0711 | G13: =VLOOKUP($A13,[1]Burgiss_Return!$B:$P,MATCH(G$2,[1]Burgiss_Return!$B$5:$P$5,0),0) -> 0.0174 | I13: =VLOOKUP($A13,[1]Burgiss_Return!$B:$P,MATCH(I$2,[1]Burgiss_Return!$B$5:$P$5,0),0) -> -0.001 | J13: =VLOOKUP($A13,[1]Burgiss_Return!$B:$P,MATCH(J$2,[1]Burgiss_Return!$B$5:$P$5,0),0) -> -0.0505 | K13: 0.0065079412 | M13: =VLOOKUP($A13,[1]Burgiss_Return!$B:$P,MATCH(M$2,[1]Burgiss_Return!$B$5:$P$5,0),0) -> -0.0043 | Q13: 0.054388048
A14: 37529 | B14: =VLOOKUP($A14,[1]Burgiss_Return!$B:$P,MATCH(B$2,[1]Burgiss_Return!$B$5:$P$5,0),0) -> -0.0398 | C14: =VLOOKUP($A14,[1]Burgiss_Return!$B:$P,MATCH(C$2,[1]Burgiss_Return!$B$5:$P$5,0),0) -> -0.0991 | D14: =VLOOKUP($A14,[1]Burgiss_Return!$B:$P,MATCH(D$2,[1]Burgiss_Return!$B$5:$P$5,0),0) -> -0.0991 | E14: =VLOOKUP($A14,[1]Burgiss_Return!$B:$P,MATCH(E$2,[1]Burgiss_Return!$B$5:$P$5,0),0) -> -0.0334 | F14: =VLOOKUP($A14,[1]Burgiss_Return!$B:$P,MATCH(F$2,[1]Burgiss_Return!$B$5:$P$5,0),0) -> -0.0593 | G14: =VLOOKUP($A14,[1]Burgiss_Return!$B:$P,MATCH(G$2,[1]Burgiss_Return!$B$5:$P$5,0),0) -> -0.0334 | I14: =VLOOKUP($A14,[1]Burgiss_Return!$B:$P,MATCH(I$2,[1]Burgiss_Return!$B$5:$P$5,0),0) -> -0.0519 | J14: =VLOOKUP($A14,[1]Burgiss_Return!$B:$P,MATCH(J$2,[1]Burgiss_Return!$B$5:$P$5,0),0) -> -0.0926 | K14: -0.0062142281 | M14: =VLOOKUP($A14,[1]Burgiss_Return!$B:$P,MATCH(M$2,[1]Burgiss_Return!$B$5:$P$5,0),0) -> 0.0039 | Q14: -0.10073231
A15: 37621 | B15: =VLOOKUP($A15,[1]Burgiss_Return!$B:$P,MATCH(B$2,[1]Burgiss_Return!$B$5:$P$5,0),0) -> 0.0208 | C15: =VLOOKUP($A15,[1]Burgiss_Return!$B:$P,MATCH(C$2,[1]Burgiss_Return!$B$5:$P$5,0),0) -> -0.1076 | D15: =VLOOKUP($A15,[1]Burgiss_Return!$B:$P,MATCH(D$2,[1]Burgiss_Return!$B$5:$P$5,0),0) -> -0.1076 | E15: =VLOOKUP($A15,[1]Burgiss_Return!$B:$P,MATCH(E$2,[1]Burgiss_Return!$B$5:$P$5,0),0) -> -0.0336 | F15: =VLOOKUP($A15,[1]Burgiss_Return!$B:$P,MATCH(F$2,[1]Burgiss_Return!$B$5:$P$5,0),0) -> -0.0763 | G15: =VLOOKUP($A15,[1]Burgiss_Return!$B:$P,MATCH(G$2,[1]Burgiss_Return!$B$5:$P$5,0),0) -> -0.0336 | I15: =VLOOKUP($A15,[1]Burgiss_Return!$B:$P,MATCH(I$2,[1]Burgiss_Return!$B$5:$P$5,0),0) -> 0.0741 | J15: =VLOOKUP($A15,[1]Burgiss_Return!$B:$P,MATCH(J$2,[1]Burgiss_Return!$B$5:$P$5,0),0) -> 0.0067 | K15: 0.021797079 | M15: =VLOOKUP($A15,[1]Burgiss_Return!$B:$P,MATCH(M$2,[1]Burgiss_Return!$B$5:$P$5,0),0) -> -0.0077 | Q15: 0.029036769
A16: 37711 | B16: =VLOOKUP($A16,[1]Burgiss_Return!$B:$P,MATCH(B$2,[1]Burgiss_Return!$B$5:$P$5,0),0) -> 0.0042 | C16: =VLOOKUP($A16,[1]Burgiss_Return!$B:$P,MATCH(C$2,[1]Burgiss_Return!$B$5:$P$5,0),0) -> -0.0468 | D16: =VLOOKUP($A16,[1]Burgiss_Return!$B:$P,MATCH(D$2,[1]Burgiss_Return!$B$5:$P$5,0),0) -> -0.0468 | E16: =VLOOKUP($A16,[1]Burgiss_Return!$B:$P,MATCH(E$2,[1]Burgiss_Return!$B$5:$P$5,0),0) -> -0.0072 | F16: =VLOOKUP($A16,[1]Burgiss_Return!$B:$P,MATCH(F$2,[1]Burgiss_Return!$B$5:$P$5,0),0) -> -0.0315 | G16: =VLOOKUP($A16,[1]Burgiss_Return!$B:$P,MATCH(G$2,[1]Burgiss_Return!$B$5:$P$5,0),0) -> -0.0072 | I16: =VLOOKUP($A16,[1]Burgiss_Return!$B:$P,MATCH(I$2,[1]Burgiss_Return!$B$5:$P$5,0),0) -> 0.0151 | J16: =VLOOKUP($A16,[1]Burgiss_Return!$B:$P,MATCH(J$2,[1]Burgiss_Return!$B$5:$P$5,0),0) -> -0.0443 | K16: 0.021230963 | M16: =VLOOKUP($A16,[1]Burgiss_Return!$B:$P,MATCH(M$2,[1]Burgiss_Return!$B$5:$P$5,0),0) -> 0.0174 | Q16: -0.017310596
A17: 37802 | B17: =VLOOKUP($A17,[1]Burgiss_Return!$B:$P,MATCH(B$2,[1]Burgiss_Return!$B$5:$P$5,0),0) -> 0.0722 | C17: =VLOOKUP($A17,[1]Burgiss_Return!$B:$P,MATCH(C$2,[1]Burgiss_Return!$B$5:$P$5,0),0) -> -0.0103 | D17: =VLOOKUP($A17,[1]Burgiss_Return!$B:$P,MATCH(D$2,[1]Burgiss_Return!$B$5:$P$5,0),0) -> -0.0103 | E17: =VLOOKUP($A17,[1]Burgiss_Return!$B:$P,MATCH(E$2,[1]Burgiss_Return!$B$5:$P$5,0),0) -> 0.0222 | F17: =VLOOKUP($A17,[1]Burgiss_Return!$B:$P,MATCH(F$2,[1]Burgiss_Return!$B$5:$P$5,0),0) -> 0.0201 | G17: =VLOOKUP($A17,[1]Burgiss_Return!$B:$P,MATCH(G$2,[1]Burgiss_Return!$B$5:$P$5,0),0) -> 0.0222 | I17: =VLOOKUP($A17,[1]Burgiss_Return!$B:$P,MATCH(I$2,[1]Burgiss_Return!$B$5:$P$5,0),0) -> 0.1353 | J17: =VLOOKUP($A17,[1]Burgiss_Return!$B:$P,MATCH(J$2,[1]Burgiss_Return!$B$5:$P$5,0),0) -> 0.0623 | K17: 0.028255806 | M17: =VLOOKUP($A17,[1]Burgiss_Return!$B:$P,MATCH(M$2,[1]Burgiss_Return!$B$5:$P$5,0),0) -> 0.0134 | Q17: 0.14436782
A18: 37894 | B18: =VLOOKUP($A18,[1]Burgiss_Return!$B:$P,MATCH(B$2,[1]Burgiss_Return!$B$5:$P$5,0),0) -> 0.0434 | C18: =VLOOKUP($A18,[1]Burgiss_Return!$B:$P,MATCH(C$2,[1]Burgiss_Return!$B$5:$P$5,0),0) -> -0.0305 | D18: =VLOOKUP($A18,[1]Burgiss_Return!$B:$P,MATCH(D$2,[1]Burgiss_Return!$B$5:$P$5,0),0) -> -0.0305 | E18: =VLOOKUP($A18,[1]Burgiss_Return!$B:$P,MATCH(E$2,[1]Burgiss_Return!$B$5:$P$5,0),0) -> 0.0398 | F18: =VLOOKUP($A18,[1]Burgiss_Return!$B:$P,MATCH(F$2,[1]Burgiss_Return!$B$5:$P$5,0),0) -> 0.0027 | G18: =VLOOKUP($A18,[1]Burgiss_Return!$B:$P,MATCH(G$2,[1]Burgiss_Return!$B$5:$P$5,0),0) -> 0.0398 | I18: =VLOOKUP($A18,[1]Burgiss_Return!$B:$P,MATCH(I$2,[1]Burgiss_Return!$B$5:$P$5,0),0) -> 0.0588 | J18: =VLOOKUP($A18,[1]Burgiss_Return!$B:$P,MATCH(J$2,[1]Burgiss_Return!$B$5:$P$5,0),0) -> 0.1035 | K18: 0.011475977 | M18: =VLOOKUP($A18,[1]Burgiss_Return!$B:$P,MATCH(M$2,[1]Burgiss_Return!$B$5:$P$5,0),0) -> 0.0165 | Q18: 0.11854139
A19: 37986 | B19: =VLOOKUP($A19,[1]Burgiss_Return!$B:$P,MATCH(B$2,[1]Burgiss_Return!$B$5:$P$5,0),0) -> 0.126 | C19: =VLOOKUP($A19,[1]Burgiss_Return!$B:$P,MATCH(C$2,[1]Burgiss_Return!$B$5:$P$5,0),0) -> 0.0167 | D19: =VLOOKUP($A19,[1]Burgiss_Return!$B:$P,MATCH(D$2,[1]Burgiss_Return!$B$5:$P$5,0),0) -> 0.0167 | E19: =VLOOKUP($A19,[1]Burgiss_Return!$B:$P,MATCH(E$2,[1]Burgiss_Return!$B$5:$P$5,0),0) -> 0.1883 | F19: =VLOOKUP($A19,[1]Burgiss_Return!$B:$P,MATCH(F$2,[1]Burgiss_Return!$B$5:$P$5,0),0) -> 0.0826 | G19: =VLOOKUP($A19,[1]Burgiss_Return!$B:$P,MATCH(G$2,[1]Burgiss_Return!$B$5:$P$5,0),0) -> 0.1883 | I19: =VLOOKUP($A19,[1]Burgiss_Return!$B:$P,MATCH(I$2,[1]Burgiss_Return!$B$5:$P$5,0),0) -> 0.0755 | J19: =VLOOKUP($A19,[1]Burgiss_Return!$B:$P,MATCH(J$2,[1]Burgiss_Return!$B$5:$P$5,0),0) -> 0.1521 | K19: 0.026332629 | M19: =VLOOKUP($A19,[1]Burgiss_Return!$B:$P,MATCH(M$2,[1]Burgiss_Return!$B$5:$P$5,0),0) -> 0.057 | Q19: 0.11851888
A20: 38077 | B20: =VLOOKUP($A20,[1]Burgiss_Return!$B:$P,MATCH(B$2,[1]Burgiss_Return!$B$5:$P$5,0),0) -> 0.0159 | C20: =VLOOKUP($A20,[1]Burgiss_Return!$B:$P,MATCH(C$2,[1]Burgiss_Return!$B$5:$P$5,0),0) -> 0.0152 | D20: =VLOOKUP($A20,[1]Burgiss_Return!$B:$P,MATCH(D$2,[1]Burgiss_Return!$B$5:$P$5,0),0) -> 0.0152 | E20: =VLOOKUP($A20,[1]Burgiss_Return!$B:$P,MATCH(E$2,[1]Burgiss_Return!$B$5:$P$5,0),0) -> 0.0362 | F20: =VLOOKUP($A20,[1]Burgiss_Return!$B:$P,MATCH(F$2,[1]Burgiss_Return!$B$5:$P$5,0),0) -> -0.0121 | G20: =VLOOKUP($A20,[1]Burgiss_Return!$B:$P,MATCH(G$2,[1]Burgiss_Return!$B$5:$P$5,0),0) -> 0.0362 | I20: =VLOOKUP($A20,[1]Burgiss_Return!$B:$P,MATCH(I$2,[1]Burgiss_Return!$B$5:$P$5,0),0) -> 0.0351 | J20: =VLOOKUP($A20,[1]Burgiss_Return!$B:$P,MATCH(J$2,[1]Burgiss_Return!$B$5:$P$5,0),0) -> 0.1377 | K20: 0.023805916 | M20: =VLOOKUP($A20,[1]Burgiss_Return!$B:$P,MATCH(M$2,[1]Burgiss_Return!$B$5:$P$5,0),0) -> 0.0184 | Q20: 0.13489849
A21: 38168 | B21: =VLOOKUP($A21,[1]Burgiss_Return!$B:$P,MATCH(B$2,[1]Burgiss_Return!$B$5:$P$5,0),0) -> 0.0519 | C21: =VLOOKUP($A21,[1]Burgiss_Return!$B:$P,MATCH(C$2,[1]Burgiss_Return!$B$5:$P$5,0),0) -> 0.003 | D21: =VLOOKUP($A21,[1]Burgiss_Return!$B:$P,MATCH(D$2,[1]Burgiss_Return!$B$5:$P$5,0),0) -> 0.003 | E21: =VLOOKUP($A21,[1]Burgiss_Return!$B:$P,MATCH(E$2,[1]Burgiss_Return!$B$5:$P$5,0),0) -> 0.0483 | F21: =VLOOKUP($A21,[1]Burgiss_Return!$B:$P,MATCH(F$2,[1]Burgiss_Return!$B$5:$P$5,0),0) -> 0.0245 | G21: =VLOOKUP($A21,[1]Burgiss_Return!$B:$P,MATCH(G$2,[1]Burgiss_Return!$B$5:$P$5,0),0) -> 0.0483 | I21: =VLOOKUP($A21,[1]Burgiss_Return!$B:$P,MATCH(I$2,[1]Burgiss_Return!$B$5:$P$5,0),0) -> 0.0313 | J21: =VLOOKUP($A21,[1]Burgiss_Return!$B:$P,MATCH(J$2,[1]Burgiss_Return!$B$5:$P$5,0),0) -> 0.0265 | K21: -0.0065285202 | M21: =VLOOKUP($A21,[1]Burgiss_Return!$B:$P,MATCH(M$2,[1]Burgiss_Return!$B$5:$P$5,0),0) -> 0.0296 | Q21: -0.041273355
A22: 38260 | B22: =VLOOKUP($A22,[1]Burgiss_Return!$B:$P,MATCH(B$2,[1]Burgiss_Return!$B$5:$P$5,0),0) -> 0.0237 | C22: =VLOOKUP($A22,[1]Burgiss_Return!$B:$P,MATCH(C$2,[1]Burgiss_Return!$B$5:$P$5,0),0) -> 0.0653 | D22: =VLOOKUP($A22,[1]Burgiss_Return!$B:$P,MATCH(D$2,[1]Burgiss_Return!$B$5:$P$5,0),0) -> 0.0653 | E22: =VLOOKUP($A22,[1]Burgiss_Return!$B:$P,MATCH(E$2,[1]Burgiss_Return!$B$5:$P$5,0),0) -> 0.0474 | F22: =VLOOKUP($A22,[1]Burgiss_Return!$B:$P,MATCH(F$2,[1]Burgiss_Return!$B$5:$P$5,0),0) -> 0.0242 | G22: =VLOOKUP($A22,[1]Burgiss_Return!$B:$P,MATCH(G$2,[1]Burgiss_Return!$B$5:$P$5,0),0) -> 0.0474 | I22: =VLOOKUP($A22,[1]Burgiss_Return!$B:$P,MATCH(I$2,[1]Burgiss_Return!$B$5:$P$5,0),0) -> 0.0452 | J22: =VLOOKUP($A22,[1]Burgiss_Return!$B:$P,MATCH(J$2,[1]Burgiss_Return!$B$5:$P$5,0),0) -> 0.0377 | K22: 0.0047303679 | M22: =VLOOKUP($A22,[1]Burgiss_Return!$B:$P,MATCH(M$2,[1]Burgiss_Return!$B$5:$P$5,0),0) -> 0.0038 | Q22: 0.07574395
A23: 38352 | B23: =VLOOKUP($A23,[1]Burgiss_Return!$B:$P,MATCH(B$2,[1]Burgiss_Return!$B$5:$P$5,0),0) -> 0.1543 | C23: =VLOOKUP($A23,[1]Burgiss_Return!$B:$P,MATCH(C$2,[1]Burgiss_Return!$B$5:$P$5,0),0) -> 0.0597 | D23: =VLOOKUP($A23,[1]Burgiss_Return!$B:$P,MATCH(D$2,[1]Burgiss_Return!$B$5:$P$5,0),0) -> 0.0597 | E23: =VLOOKUP($A23,[1]Burgiss_Return!$B:$P,MATCH(E$2,[1]Burgiss_Return!$B$5:$P$5,0),0) -> 0.1506 | F23: =VLOOKUP($A23,[1]Burgiss_Return!$B:$P,MATCH(F$2,[1]Burgiss_Return!$B$5:$P$5,0),0) -> 0.0959 | G23: =VLOOKUP($A23,[1]Burgiss_Return!$B:$P,MATCH(G$2,[1]Burgiss_Return!$B$5:$P$5,0),0) -> 0.1506 | I23: =VLOOKUP($A23,[1]Burgiss_Return!$B:$P,MATCH(I$2,[1]Burgiss_Return!$B$5:$P$5,0),0) -> 0.101 | J23: =VLOOKUP($A23,[1]Burgiss_Return!$B:$P,MATCH(J$2,[1]Burgiss_Return!$B$5:$P$5,0),0) -> 0.1219 | K23: 0.035564989 | M23: =VLOOKUP($A23,[1]Burgiss_Return!$B:$P,MATCH(M$2,[1]Burgiss_Return!$B$5:$P$5,0),0) -> 0.1702 | Q23: 0.17869933
... A30: 38990 | B30: =VLOOKUP($A30,[1]Burgiss_Return!$B:$P,MATCH(B$2,[1]Burgiss_Return!$B$5:$P$5,0),0) -> 0.0321 | C30: =VLOOKUP($A30,[1]Burgiss_Return!$B:$P,MATCH(C$2,[1]Burgiss_Return!$B$5:$P$5,0),0) -> 0.0145 | D30: =VLOOKUP($A30,[1]Burgiss_Return!$B:$P,MATCH(D$2,[1]Burgiss_Return!$B$5:$P$5,0),0) -> 0.0145 | E30: =VLOOKUP($A30,[1]Burgiss_Return!$B:$P,MATCH(E$2,[1]Burgiss_Return!$B$5:$P$5,0),0) -> 0.0394 | F30: =VLOOKUP($A30,[1]Burgiss_Return!$B:$P,MATCH(F$2,[1]Burgiss_Return!$B$5:$P$5,0),0) -> 0.0286 | G30: =VLOOKUP($A30,[1]Burgiss_Return!$B:$P,MATCH(G$2,[1]Burgiss_Return!$B$5:$P$5,0),0) -> 0.0394 | I30: =VLOOKUP($A30,[1]Burgiss_Return!$B:$P,MATCH(I$2,[1]Burgiss_Return!$B$5:$P$5,0),0) -> 0.0283 | J30: =VLOOKUP($A30,[1]Burgiss_Return!$B:$P,MATCH(J$2,[1]Burgiss_Return!$B$5:$P$5,0),0) -> -0.0008 | K30: 0.0046450011 | M30: =VLOOKUP($A30,[1]Burgiss_Return!$B:$P,MATCH(M$2,[1]Burgiss_Return!$B$5:$P$5,0),0) -> 0.0343 | Q30: 0.09918614
A31: 39082 | B31: =VLOOKUP($A31,[1]Burgiss_Return!$B:$P,MATCH(B$2,[1]Burgiss_Return!$B$5:$P$5,0),0) -> 0.1756 | C31: =VLOOKUP($A31,[1]Burgiss_Return!$B:$P,MATCH(C$2,[1]Burgiss_Return!$B$5:$P$5,0),0) -> 0.0914 | D31: =VLOOKUP($A31,[1]Burgiss_Return!$B:$P,MATCH(D$2,[1]Burgiss_Return!$B$5:$P$5,0),0) -> 0.0914 | E31: =VLOOKUP($A31,[1]Burgiss_Return!$B:$P,MATCH(E$2,[1]Burgiss_Return!$B$5:$P$5,0),0) -> 0.1077 | F31: =VLOOKUP($A31,[1]Burgiss_Return!$B:$P,MATCH(F$2,[1]Burgiss_Return!$B$5:$P$5,0),0) -> 0.0696 | G31: =VLOOKUP($A31,[1]Burgiss_Return!$B:$P,MATCH(G$2,[1]Burgiss_Return!$B$5:$P$5,0),0) -> 0.1077 | I31: =VLOOKUP($A31,[1]Burgiss_Return!$B:$P,MATCH(I$2,[1]Burgiss_Return!$B$5:$P$5,0),0) -> 0.0764 | J31: =VLOOKUP($A31,[1]Burgiss_Return!$B:$P,MATCH(J$2,[1]Burgiss_Return!$B$5:$P$5,0),0) -> 0.1133 | K31: 0.039354702 | M31: =VLOOKUP($A31,[1]Burgiss_Return!$B:$P,MATCH(M$2,[1]Burgiss_Return!$B$5:$P$5,0),0) -> 0.1758 | Q31: 0.14040027 | R31: =VLOOKUP($A31,[1]Burgiss_Return!$B:$P,MATCH(R$2,[1]Burgiss_Return!$B$5:$P$5,0),0) -> -0.0407 | S31: =VLOOKUP($A31,[1]Burgiss_Return!$B:$P,MATCH(S$2,[1]Burgiss_Return!$B$5:$P$5,0),0) -> -0.0407 | T31: =VLOOKUP($A31,[1]Burgiss_Return!$B:$P,MATCH(T$2,[1]Burgiss_Return!$B$5:$P$5,0),0) -> -0.0407 | U31: =VLOOKUP($A31,[1]Burgiss_Return!$B:$P,MATCH(U$2,[1]Burgiss_Return!$B$5:$P$5,0),0) -> -0.0407
A32: 39172 | B32: =VLOOKUP($A32,[1]Burgiss_Return!$B:$P,MATCH(B$2,[1]Burgiss_Return!$B$5:$P$5,0),0) -> 0.0543 | C32: =VLOOKUP($A32,[1]Burgiss_Return!$B:$P,MATCH(C$2,[1]Burgiss_Return!$B$5:$P$5,0),0) -> 0.0115 | D32: =VLOOKUP($A32,[1]Burgiss_Return!$B:$P,MATCH(D$2,[1]Burgiss_Return!$B$5:$P$5,0),0) -> 0.0115 | E32: =VLOOKUP($A32,[1]Burgiss_Return!$B:$P,MATCH(E$2,[1]Burgiss_Return!$B$5:$P$5,0),0) -> 0.0364 | F32: =VLOOKUP($A32,[1]Burgiss_Return!$B:$P,MATCH(F$2,[1]Burgiss_Return!$B$5:$P$5,0),0) -> 0.042 | G32: =VLOOKUP($A32,[1]Burgiss_Return!$B:$P,MATCH(G$2,[1]Burgiss_Return!$B$5:$P$5,0),0) -> 0.0364 | I32: =VLOOKUP($A32,[1]Burgiss_Return!$B:$P,MATCH(I$2,[1]Burgiss_Return!$B$5:$P$5,0),0) -> 0.0474 | J32: =VLOOKUP($A32,[1]Burgiss_Return!$B:$P,MATCH(J$2,[1]Burgiss_Return!$B$5:$P$5,0),0) -> 0.0411 | K32: 0.031239626 | M32: =VLOOKUP($A32,[1]Burgiss_Return!$B:$P,MATCH(M$2,[1]Burgiss_Return!$B$5:$P$5,0),0) -> 0.1033 | Q32: 0.062226222 | R32: =VLOOKUP($A32,[1]Burgiss_Return!$B:$P,MATCH(R$2,[1]Burgiss_Return!$B$5:$P$5,0),0) -> 0.0054 | S32: =VLOOKUP($A32,[1]Burgiss_Return!$B:$P,MATCH(S$2,[1]Burgiss_Return!$B$5:$P$5,0),0) -> 0.0054 | T32: =VLOOKUP($A32,[1]Burgiss_Return!$B:$P,MATCH(T$2,[1]Burgiss_Return!$B$5:$P$5,0),0) -> 0.0054 | U32: =VLOOKUP($A32,[1]Burgiss_Return!$B:$P,MATCH(U$2,[1]Burgiss_Return!$B$5:$P$5,0),0) -> 0.0054
A33: 39263 | B33: =VLOOKUP($A33,[1]Burgiss_Return!$B:$P,MATCH(B$2,[1]Burgiss_Return!$B$5:$P$5,0),0) -> 0.1117 | C33: =VLOOKUP($A33,[1]Burgiss_Return!$B:$P,MATCH(C$2,[1]Burgiss_Return!$B$5:$P$5,0),0) -> 0.0789 | D33: =VLOOKUP($A33,[1]Burgiss_Return!$B:$P,MATCH(D$2,[1]Burgiss_Return!$B$5:$P$5,0),0) -> 0.0789 | E33: =VLOOKUP($A33,[1]Burgiss_Return!$B:$P,MATCH(E$2,[1]Burgiss_Return!$B$5:$P$5,0),0) -> 0.0672 | F33: =VLOOKUP($A33,[1]Burgiss_Return!$B:$P,MATCH(F$2,[1]Burgiss_Return!$B$5:$P$5,0),0) -> 0.0641 | G33: =VLOOKUP($A33,[1]Burgiss_Return!$B:$P,MATCH(G$2,[1]Burgiss_Return!$B$5:$P$5,0),0) -> 0.0672 | I33: =VLOOKUP($A33,[1]Burgiss_Return!$B:$P,MATCH(I$2,[1]Burgiss_Return!$B$5:$P$5,0),0) -> 0.0586 | J33: =VLOOKUP($A33,[1]Burgiss_Return!$B:$P,MATCH(J$2,[1]Burgiss_Return!$B$5:$P$5,0),0) -> 0.1631 | K33: 0.032940973 | M33: =VLOOKUP($A33,[1]Burgiss_Return!$B:$P,MATCH(M$2,[1]Burgiss_Return!$B$5:$P$5,0),0) -> 0.0523 | Q33: -0.058512745 | R33: =VLOOKUP($A33,[1]Burgiss_Return!$B:$P,MATCH(R$2,[1]Burgiss_Return!$B$5:$P$5,0),0) -> 0.0344 | S33: =VLOOKUP($A33,[1]Burgiss_Return!$B:$P,MATCH(S$2,[1]Burgiss_Return!$B$5:$P$5,0),0) -> 0.0344 | T33: =VLOOKUP($A33,[1]Burgiss_Return!$B:$P,MATCH(T$2,[1]Burgiss_Return!$B$5:$P$5,0),0) -> 0.0344 | U33: =VLOOKUP($A33,[1]Burgiss_Return!$B:$P,MATCH(U$2,[1]Burgiss_Return!$B$5:$P$5,0),0) -> 0.0344
A34: 39355 | B34: =VLOOKUP($A34,[1]Burgiss_Return!$B:$P,MATCH(B$2,[1]Burgiss_Return!$B$5:$P$5,0),0) -> 0.0283 | C34: =VLOOKUP($A34,[1]Burgiss_Return!$B:$P,MATCH(C$2,[1]Burgiss_Return!$B$5:$P$5,0),0) -> 0.0236 | D34: =VLOOKUP($A34,[1]Burgiss_Return!$B:$P,MATCH(D$2,[1]Burgiss_Return!$B$5:$P$5,0),0) -> 0.0236 | E34: =VLOOKUP($A34,[1]Burgiss_Return!$B:$P,MATCH(E$2,[1]Burgiss_Return!$B$5:$P$5,0),0) -> 0.0795 | F34: =VLOOKUP($A34,[1]Burgiss_Return!$B:$P,MATCH(F$2,[1]Burgiss_Return!$B$5:$P$5,0),0) -> 0.0499 | G34: =VLOOKUP($A34,[1]Burgiss_Return!$B:$P,MATCH(G$2,[1]Burgiss_Return!$B$5:$P$5,0),0) -> 0.0795 | I34: =VLOOKUP($A34,[1]Burgiss_Return!$B:$P,MATCH(I$2,[1]Burgiss_Return!$B$5:$P$5,0),0) -> -0.0083 | J34: =VLOOKUP($A34,[1]Burgiss_Return!$B:$P,MATCH(J$2,[1]Burgiss_Return!$B$5:$P$5,0),0) -> 0.0799 | K34: -0.0044834015 | M34: =VLOOKUP($A34,[1]Burgiss_Return!$B:$P,MATCH(M$2,[1]Burgiss_Return!$B$5:$P$5,0),0) -> -0.0012 | Q34: 0.036556755 | R34: =VLOOKUP($A34,[1]Burgiss_Return!$B:$P,MATCH(R$2,[1]Burgiss_Return!$B$5:$P$5,0),0) -> 0.0002 | S34: =VLOOKUP($A34,[1]Burgiss_Return!$B:$P,MATCH(S$2,[1]Burgiss_Return!$B$5:$P$5,0),0) -> 0.0002 | T34: =VLOOKUP($A34,[1]Burgiss_Return!$B:$P,MATCH(T$2,[1]Burgiss_Return!$B$5:$P$5,0),0) -> 0.0002 | U34: =VLOOKUP($A34,[1]Burgiss_Return!$B:$P,MATCH(U$2,[1]Burgiss_Return!$B$5:$P$5,0),0) -> 0.0002
A35: 39447 | B35: =VLOOKUP($A35,[1]Burgiss_Return!$B:$P,MATCH(B$2,[1]Burgiss_Return!$B$5:$P$5,0),0) -> 0.0369 | C35: =VLOOKUP($A35,[1]Burgiss_Return!$B:$P,MATCH(C$2,[1]Burgiss_Return!$B$5:$P$5,0),0) -> 0.0386 | D35: =VLOOKUP($A35,[1]Burgiss_Return!$B:$P,MATCH(D$2,[1]Burgiss_Return!$B$5:$P$5,0),0) -> 0.0386 | E35: =VLOOKUP($A35,[1]Burgiss_Return!$B:$P,MATCH(E$2,[1]Burgiss_Return!$B$5:$P$5,0),0) -> 0.0523 | F35: =VLOOKUP($A35,[1]Burgiss_Return!$B:$P,MATCH(F$2,[1]Burgiss_Return!$B$5:$P$5,0),0) -> 0.0562 | G35: =VLOOKUP($A35,[1]Burgiss_Return!$B:$P,MATCH(G$2,[1]Burgiss_Return!$B$5:$P$5,0),0) -> 0.0523 | I35: =VLOOKUP($A35,[1]Burgiss_Return!$B:$P,MATCH(I$2,[1]Burgiss_Return!$B$5:$P$5,0),0) -> -0.0351 | J35: =VLOOKUP($A35,[1]Burgiss_Return!$B:$P,MATCH(J$2,[1]Burgiss_Return!$B$5:$P$5,0),0) -> 0.1033 | K35: 0.015416412 | M35: =VLOOKUP($A35,[1]Burgiss_Return!$B:$P,MATCH(M$2,[1]Burgiss_Return!$B$5:$P$5,0),0) -> 0.0075 | Q35: -0.10245851 | R35: =VLOOKUP($A35,[1]Burgiss_Return!$B:$P,MATCH(R$2,[1]Burgiss_Return!$B$5:$P$5,0),0) -> 0.0967 | S35: =VLOOKUP($A35,[1]Burgiss_Return!$B:$P,MATCH(S$2,[1]Burgiss_Return!$B$5:$P$5,0),0) -> 0.0967 | T35: =VLOOKUP($A35,[1]Burgiss_Return!$B:$P,MATCH(T$2,[1]Burgiss_Return!$B$5:$P$5,0),0) -> 0.0967 | U35: =VLOOKUP($A35,[1]Burgiss_Return!$B:$P,MATCH(U$2,[1]Burgiss_Return!$B$5:$P$5,0),0) -> 0.0967
A36: 39538 | B36: =VLOOKUP($A36,[1]Burgiss_Return!$B:$P,MATCH(B$2,[1]Burgiss_Return!$B$5:$P$5,0),0) -> 0.0035 | C36: =VLOOKUP($A36,[1]Burgiss_Return!$B:$P,MATCH(C$2,[1]Burgiss_Return!$B$5:$P$5,0),0) -> -0.0136 | D36: =VLOOKUP($A36,[1]Burgiss_Return!$B:$P,MATCH(D$2,[1]Burgiss_Return!$B$5:$P$5,0),0) -> -0.0136 | E36: =VLOOKUP($A36,[1]Burgiss_Return!$B:$P,MATCH(E$2,[1]Burgiss_Return!$B$5:$P$5,0),0) -> 0.0117 | F36: =VLOOKUP($A36,[1]Burgiss_Return!$B:$P,MATCH(F$2,[1]Burgiss_Return!$B$5:$P$5,0),0) -> 0.0071 | G36: =VLOOKUP($A36,[1]Burgiss_Return!$B:$P,MATCH(G$2,[1]Burgiss_Return!$B$5:$P$5,0),0) -> 0.0117 | I36: =VLOOKUP($A36,[1]Burgiss_Return!$B:$P,MATCH(I$2,[1]Burgiss_Return!$B$5:$P$5,0),0) -> -0.0373 | J36: =VLOOKUP($A36,[1]Burgiss_Return!$B:$P,MATCH(J$2,[1]Burgiss_Return!$B$5:$P$5,0),0) -> -0.0756 | K36: -0.028564399 | L36: 0.013174 | M36: =VLOOKUP($A36,[1]Burgiss_Return!$B:$P,MATCH(M$2,[1]Burgiss_Return!$B$5:$P$5,0),0) -> 0.0143 | N36: 0.013174 | Q36: -0.05629264 | R36: =VLOOKUP($A36,[1]Burgiss_Return!$B:$P,MATCH(R$2,[1]Burgiss_Return!$B$5:$P$5,0),0) -> 0.0354 | S36: =VLOOKUP($A36,[1]Burgiss_Return!$B:$P,MATCH(S$2,[1]Burgiss_Return!$B$5:$P$5,0),0) -> 0.0354 | T36: =VLOOKUP($A36,[1]Burgiss_Return!$B:$P,MATCH(T$2,[1]Burgiss_Return!$B$5:$P$5,0),0) -> 0.0354 | U36: =VLOOKUP($A36,[1]Burgiss_Return!$B:$P,MATCH(U$2,[1]Burgiss_Return!$B$5:$P$5,0),0) -> 0.0354
A37: 39629 | B37: =VLOOKUP($A37,[1]Burgiss_Return!$B:$P,MATCH(B$2,[1]Burgiss_Return!$B$5:$P$5,0),0) -> -0.0159 | C37: =VLOOKUP($A37,[1]Burgiss_Return!$B:$P,MATCH(C$2,[1]Burgiss_Return!$B$5:$P$5,0),0) -> -0.0057 | D37: =VLOOKUP($A37,[1]Burgiss_Return!$B:$P,MATCH(D$2,[1]Burgiss_Return!$B$5:$P$5,0),0) -> -0.0057 | E37: =VLOOKUP($A37,[1]Burgiss_Return!$B:$P,MATCH(E$2,[1]Burgiss_Return!$B$5:$P$5,0),0) -> -0.0065 | F37: =VLOOKUP($A37,[1]Burgiss_Return!$B:$P,MATCH(F$2,[1]Burgiss_Return!$B$5:$P$5,0),0) -> -0.0083 | G37: =VLOOKUP($A37,[1]Burgiss_Return!$B:$P,MATCH(G$2,[1]Burgiss_Return!$B$5:$P$5,0),0) -> -0.0065 | I37: =VLOOKUP($A37,[1]Burgiss_Return!$B:$P,MATCH(I$2,[1]Burgiss_Return!$B$5:$P$5,0),0) -> 0.0435 | J37: =VLOOKUP($A37,[1]Burgiss_Return!$B:$P,MATCH(J$2,[1]Burgiss_Return!$B$5:$P$5,0),0) -> -0.0411 | K37: 0.016810447 | L37: 0.00666 | M37: =VLOOKUP($A37,[1]Burgiss_Return!$B:$P,MATCH(M$2,[1]Burgiss_Return!$B$5:$P$5,0),0) -> -0.0239 | N37: 0.00666 | Q37: -0.085597679 | R37: =VLOOKUP($A37,[1]Burgiss_Return!$B:$P,MATCH(R$2,[1]Burgiss_Return!$B$5:$P$5,0),0) -> 0.0308 | S37: =VLOOKUP($A37,[1]Burgiss_Return!$B:$P,MATCH(S$2,[1]Burgiss_Return!$B$5:$P$5,0),0) -> 0.0308 | T37: =VLOOKUP($A37,[1]Burgiss_Return!$B:$P,MATCH(T$2,[1]Burgiss_Return!$B$5:$P$5,0),0) -> 0.0308 | U37: =VLOOKUP($A37,[1]Burgiss_Return!$B:$P,MATCH(U$2,[1]Burgiss_Return!$B$5:$P$5,0),0) -> 0.0308
A38: 39721 | B38: =VLOOKUP($A38,[1]Burgiss_Return!$B:$P,MATCH(B$2,[1]Burgiss_Return!$B$5:$P$5,0),0) -> -0.1017 | C38: =VLOOKUP($A38,[1]Burgiss_Return!$B:$P,MATCH(C$2,[1]Burgiss_Return!$B$5:$P$5,0),0) -> -0.03 | D38: =VLOOKUP($A38,[1]Burgiss_Return!$B:$P,MATCH(D$2,[1]Burgiss_Return!$B$5:$P$5,0),0) -> -0.03 | E38: =VLOOKUP($A38,[1]Burgiss_Return!$B:$P,MATCH(E$2,[1]Burgiss_Return!$B$5:$P$5,0),0) -> -0.0339 | F38: =VLOOKUP($A38,[1]Burgiss_Return!$B:$P,MATCH(F$2,[1]Burgiss_Return!$B$5:$P$5,0),0) -> -0.0703 | G38: =VLOOKUP($A38,[1]Burgiss_Return!$B:$P,MATCH(G$2,[1]Burgiss_Return!$B$5:$P$5,0),0) -> -0.0339 | I38: =VLOOKUP($A38,[1]Burgiss_Return!$B:$P,MATCH(I$2,[1]Burgiss_Return!$B$5:$P$5,0),0) -> -0.1325 | J38: =VLOOKUP($A38,[1]Burgiss_Return!$B:$P,MATCH(J$2,[1]Burgiss_Return!$B$5:$P$5,0),0) -> -0.0909 | K38: -0.083556744 | L38: -0.079068 | M38: =VLOOKUP($A38,[1]Burgiss_Return!$B:$P,MATCH(M$2,[1]Burgiss_Return!$B$5:$P$5,0),0) -> -0.0995 | N38: -0.079068 | Q38: -0.10410579 | R38: =VLOOKUP($A38,[1]Burgiss_Return!$B:$P,MATCH(R$2,[1]Burgiss_Return!$B$5:$P$5,0),0) -> -0.0922 | S38: =VLOOKUP($A38,[1]Burgiss_Return!$B:$P,MATCH(S$2,[1]Burgiss_Return!$B$5:$P$5,0),0) -> -0.0922 | T38: =VLOOKUP($A38,[1]Burgiss_Return!$B:$P,MATCH(T$2,[1]Burgiss_Return!$B$5:$P$5,0),0) -> -0.0922 | U38: =VLOOKUP($A38,[1]Burgiss_Return!$B:$P,MATCH(U$2,[1]Burgiss_Return!$B$5:$P$5,0),0) -> -0.0922
A39: 39813 | B39: =VLOOKUP($A39,[1]Burgiss_Return!$B:$P,MATCH(B$2,[1]Burgiss_Return!$B$5:$P$5,0),0) -> -0.1887 | C39: =VLOOKUP($A39,[1]Burgiss_Return!$B:$P,MATCH(C$2,[1]Burgiss_Return!$B$5:$P$5,0),0) -> -0.1139 | D39: =VLOOKUP($A39,[1]Burgiss_Return!$B:$P,MATCH(D$2,[1]Burgiss_Return!$B$5:$P$5,0),0) -> -0.1139 | E39: =VLOOKUP($A39,[1]Burgiss_Return!$B:$P,MATCH(E$2,[1]Burgiss_Return!$B$5:$P$5,0),0) -> -0.161 | F39: =VLOOKUP($A39,[1]Burgiss_Return!$B:$P,MATCH(F$2,[1]Burgiss_Return!$B$5:$P$5,0),0) -> -0.1435 | G39: =VLOOKUP($A39,[1]Burgiss_Return!$B:$P,MATCH(G$2,[1]Burgiss_Return!$B$5:$P$5,0),0) -> -0.161 | I39: =VLOOKUP($A39,[1]Burgiss_Return!$B:$P,MATCH(I$2,[1]Burgiss_Return!$B$5:$P$5,0),0) -> -0.1982 | J39: =VLOOKUP($A39,[1]Burgiss_Return!$B:$P,MATCH(J$2,[1]Burgiss_Return!$B$5:$P$5,0),0) -> -0.1738 | K39: -0.11474976 | L39: -0.154965 | M39: =VLOOKUP($A39,[1]Burgiss_Return!$B:$P,MATCH(M$2,[1]Burgiss_Return!$B$5:$P$5,0),0) -> -0.269 | N39: -0.154965 | Q39: -0.32378532 | R39: =VLOOKUP($A39,[1]Burgiss_Return!$B:$P,MATCH(R$2,[1]Burgiss_Return!$B$5:$P$5,0),0) -> -0.1083 | S39: =VLOOKUP($A39,[1]Burgiss_Return!$B:$P,MATCH(S$2,[1]Burgiss_Return!$B$5:$P$5,0),0) -> -0.1083 | T39: =VLOOKUP($A39,[1]Burgiss_Return!$B:$P,MATCH(T$2,[1]Burgiss_Return!$B$5:$P$5,0),0) -> -0.1083 | U39: =VLOOKUP($A39,[1]Burgiss_Return!$B:$P,MATCH(U$2,[1]Burgiss_Return!$B$5:$P$5,0),0) -> -0.1083
A40: 39903 | B40: =VLOOKUP($A40,[1]Burgiss_Return!$B:$P,MATCH(B$2,[1]Burgiss_Return!$B$5:$P$5,0),0) -> -0.0477 | C40: =VLOOKUP($A40,[1]Burgiss_Return!$B:$P,MATCH(C$2,[1]Burgiss_Return!$B$5:$P$5,0),0) -> -0.0253 | D40: =VLOOKUP($A40,[1]Burgiss_Return!$B:$P,MATCH(D$2,[1]Burgiss_Return!$B$5:$P$5,0),0) -> -0.0253 | E40: =VLOOKUP($A40,[1]Burgiss_Return!$B:$P,MATCH(E$2,[1]Burgiss_Return!$B$5:$P$5,0),0) -> -0.0282 | F40: =VLOOKUP($A40,[1]Burgiss_Return!$B:$P,MATCH(F$2,[1]Burgiss_Return!$B$5:$P$5,0),0) -> -0.0421 | G40: =VLOOKUP($A40,[1]Burgiss_Return!$B:$P,MATCH(G$2,[1]Burgiss_Return!$B$5:$P$5,0),0) -> -0.0282 | I40: =VLOOKUP($A40,[1]Burgiss_Return!$B:$P,MATCH(I$2,[1]Burgiss_Return!$B$5:$P$5,0),0) -> -0.0426 | J40: =VLOOKUP($A40,[1]Burgiss_Return!$B:$P,MATCH(J$2,[1]Burgiss_Return!$B$5:$P$5,0),0) -> -0.0038 | K40: 0.007082346 | L40: -0.111865 | M40: =VLOOKUP($A40,[1]Burgiss_Return!$B:$P,MATCH(M$2,[1]Burgiss_Return!$B$5:$P$5,0),0) -> -0.1156 | N40: -0.111865 | Q40: -0.22094595 | R40: =VLOOKUP($A40,[1]Burgiss_Return!$B:$P,MATCH(R$2,[1]Burgiss_Return!$B$5:$P$5,0),0) -> -0.0706 | S40: =VLOOKUP($A40,[1]Burgiss_Return!$B:$P,MATCH(S$2,[1]Burgiss_Return!$B$5:$P$5,0),0) -> -0.0706 | T40: =VLOOKUP($A40,[1]Burgiss_Return!$B:$P,MATCH(T$2,[1]Burgiss_Return!$B$5:$P$5,0),0) -> -0.0706 | U40: =VLOOKUP($A40,[1]Burgiss_Return!$B:$P,MATCH(U$2,[1]Burgiss_Return!$B$5:$P$5,0),0) -> -0.0706
A41: 39994 | B41: =VLOOKUP($A41,[1]Burgiss_Return!$B:$P,MATCH(B$2,[1]Burgiss_Return!$B$5:$P$5,0),0) -> 0.0537 | C41: =VLOOKUP($A41,[1]Burgiss_Return!$B:$P,MATCH(C$2,[1]Burgiss_Return!$B$5:$P$5,0),0) -> 0.0115 | D41: =VLOOKUP($A41,[1]Burgiss_Return!$B:$P,MATCH(D$2,[1]Burgiss_Return!$B$5:$P$5,0),0) -> 0.0115 | E41: =VLOOKUP($A41,[1]Burgiss_Return!$B:$P,MATCH(E$2,[1]Burgiss_Return!$B$5:$P$5,0),0) -> -0.0242 | F41: =VLOOKUP($A41,[1]Burgiss_Return!$B:$P,MATCH(F$2,[1]Burgiss_Return!$B$5:$P$5,0),0) -> -0.0116 | G41: =VLOOKUP($A41,[1]Burgiss_Return!$B:$P,MATCH(G$2,[1]Burgiss_Return!$B$5:$P$5,0),0) -> -0.0242 | I41: =VLOOKUP($A41,[1]Burgiss_Return!$B:$P,MATCH(I$2,[1]Burgiss_Return!$B$5:$P$5,0),0) -> 0.2705 | J41: =VLOOKUP($A41,[1]Burgiss_Return!$B:$P,MATCH(J$2,[1]Burgiss_Return!$B$5:$P$5,0),0) -> 0.148 | K41: 0.03874805 | L41: -0.021386 | M41: =VLOOKUP($A41,[1]Burgiss_Return!$B:$P,MATCH(M$2,[1]Burgiss_Return!$B$5:$P$5,0),0) -> -0.1236 | N41: -0.021386 | Q41: 0.35905638 | R41: =VLOOKUP($A41,[1]Burgiss_Return!$B:$P,MATCH(R$2,[1]Burgiss_Return!$B$5:$P$5,0),0) -> 0.0405 | S41: =VLOOKUP($A41,[1]Burgiss_Return!$B:$P,MATCH(S$2,[1]Burgiss_Return!$B$5:$P$5,0),0) -> 0.0405 | T41: =VLOOKUP($A41,[1]Burgiss_Return!$B:$P,MATCH(T$2,[1]Burgiss_Return!$B$5:$P$5,0),0) -> 0.0405 | U41: =VLOOKUP($A41,[1]Burgiss_Return!$B:$P,MATCH(U$2,[1]Burgiss_Return!$B$5:$P$5,0),0) -> 0.0405
A42: 40086 | B42: =VLOOKUP($A42,[1]Burgiss_Return!$B:$P,MATCH(B$2,[1]Burgiss_Return!$B$5:$P$5,0),0) -> 0.0798 | C42: =VLOOKUP($A42,[1]Burgiss_Return!$B:$P,MATCH(C$2,[1]Burgiss_Return!$B$5:$P$5,0),0) -> 0.0173 | D42: =VLOOKUP($A42,[1]Burgiss_Return!$B:$P,MATCH(D$2,[1]Burgiss_Return!$B$5:$P$5,0),0) -> 0.0173 | E42: =VLOOKUP($A42,[1]Burgiss_Return!$B:$P,MATCH(E$2,[1]Burgiss_Return!$B$5:$P$5,0),0) -> 0.0257 | F42: =VLOOKUP($A42,[1]Burgiss_Return!$B:$P,MATCH(F$2,[1]Burgiss_Return!$B$5:$P$5,0),0) -> 0.0402 | G42: =VLOOKUP($A42,[1]Burgiss_Return!$B:$P,MATCH(G$2,[1]Burgiss_Return!$B$5:$P$5,0),0) -> 0.0257 | I42: =VLOOKUP($A42,[1]Burgiss_Return!$B:$P,MATCH(I$2,[1]Burgiss_Return!$B$5:$P$5,0),0) -> 0.1758 | J42: =VLOOKUP($A42,[1]Burgiss_Return!$B:$P,MATCH(J$2,[1]Burgiss_Return!$B$5:$P$5,0),0) -> 0.0744 | K42: 0.036810569 | L42: -0.023272 | M42: =VLOOKUP($A42,[1]Burgiss_Return!$B:$P,MATCH(M$2,[1]Burgiss_Return!$B$5:$P$5,0),0) -> -0.0386 | N42: -0.023272 | Q42: 0.25081974 | R42: =VLOOKUP($A42,[1]Burgiss_Return!$B:$P,MATCH(R$2,[1]Burgiss_Return!$B$5:$P$5,0),0) -> 0.019 | S42: =VLOOKUP($A42,[1]Burgiss_Return!$B:$P,MATCH(S$2,[1]Burgiss_Return!$B$5:$P$5,0),0) -> 0.019 | T42: =VLOOKUP($A42,[1]Burgiss_Return!$B:$P,MATCH(T$2,[1]Burgiss_Return!$B$5:$P$5,0),0) -> 0.019 | U42: =VLOOKUP($A42,[1]Burgiss_Return!$B:$P,MATCH(U$2,[1]Burgiss_Return!$B$5:$P$5,0),0) -> 0.019
A43: 40178 | B43: =VLOOKUP($A43,[1]Burgiss_Return!$B:$P,MATCH(B$2,[1]Burgiss_Return!$B$5:$P$5,0),0) -> 0.0649 | C43: =VLOOKUP($A43,[1]Burgiss_Return!$B:$P,MATCH(C$2,[1]Burgiss_Return!$B$5:$P$5,0),0) -> 0.043 | D43: =VLOOKUP($A43,[1]Burgiss_Return!$B:$P,MATCH(D$2,[1]Burgiss_Return!$B$5:$P$5,0),0) -> 0.043 | E43: =VLOOKUP($A43,[1]Burgiss_Return!$B:$P,MATCH(E$2,[1]Burgiss_Return!$B$5:$P$5,0),0) -> 0.0725 | F43: =VLOOKUP($A43,[1]Burgiss_Return!$B:$P,MATCH(F$2,[1]Burgiss_Return!$B$5:$P$5,0),0) -> 0.0506 | G43: =VLOOKUP($A43,[1]Burgiss_Return!$B:$P,MATCH(G$2,[1]Burgiss_Return!$B$5:$P$5,0),0) -> 0.0725 | I43: =VLOOKUP($A43,[1]Burgiss_Return!$B:$P,MATCH(I$2,[1]Burgiss_Return!$B$5:$P$5,0),0) -> 0.0867 | J43: =VLOOKUP($A43,[1]Burgiss_Return!$B:$P,MATCH(J$2,[1]Burgiss_Return!$B$5:$P$5,0),0) -> 0.1164 | K43: 0.010942709 | L43: -0.002224 | M43: =VLOOKUP($A43,[1]Burgiss_Return!$B:$P,MATCH(M$2,[1]Burgiss_Return!$B$5:$P$5,0),0) -> -0.1196 | N43: -0.002224 | Q43: 0.043954856 | R43: =VLOOKUP($A43,[1]Burgiss_Return!$B:$P,MATCH(R$2,[1]Burgiss_Return!$B$5:$P$5,0),0) -> -0.002 | S43: =VLOOKUP($A43,[1]Burgiss_Return!$B:$P,MATCH(S$2,[1]Burgiss_Return!$B$5:$P$5,0),0) -> -0.002 | T43: =VLOOKUP($A43,[1]Burgiss_Return!$B:$P,MATCH(T$2,[1]Burgiss_Return!$B$5:$P$5,0),0) -> -0.002 | U43: =VLOOKUP($A43,[1]Burgiss_Return!$B:$P,MATCH(U$2,[1]Burgiss_Return!$B$5:$P$5,0),0) -> -0.002
A44: 40268 | B44: =VLOOKUP($A44,[1]Burgiss_Return!$B:$P,MATCH(B$2,[1]Burgiss_Return!$B$5:$P$5,0),0) -> 0.0273 | C44: =VLOOKUP($A44,[1]Burgiss_Return!$B:$P,MATCH(C$2,[1]Burgiss_Return!$B$5:$P$5,0),0) -> 0.005 | D44: =VLOOKUP($A44,[1]Burgiss_Return!$B:$P,MATCH(D$2,[1]Burgiss_Return!$B$5:$P$5,0),0) -> 0.005 | E44: =VLOOKUP($A44,[1]Burgiss_Return!$B:$P,MATCH(E$2,[1]Burgiss_Return!$B$5:$P$5,0),0) -> 0.0169 | F44: =VLOOKUP($A44,[1]Burgiss_Return!$B:$P,MATCH(F$2,[1]Burgiss_Return!$B$5:$P$5,0),0) -> 0.0106 | G44: =VLOOKUP($A44,[1]Burgiss_Return!$B:$P,MATCH(G$2,[1]Burgiss_Return!$B$5:$P$5,0),0) -> 0.0169 | I44: =VLOOKUP($A44,[1]Burgiss_Return!$B:$P,MATCH(I$2,[1]Burgiss_Return!$B$5:$P$5,0),0) -> 0.055 | J44: =VLOOKUP($A44,[1]Burgiss_Return!$B:$P,MATCH(J$2,[1]Burgiss_Return!$B$5:$P$5,0),0) -> 0.0394 | K44: 0.016997172 | L44: 0.005386 | M44: =VLOOKUP($A44,[1]Burgiss_Return!$B:$P,MATCH(M$2,[1]Burgiss_Return!$B$5:$P$5,0),0) -> 0.0051 | N44: 0.005386 | Q44: 0.039655244 | R44: =VLOOKUP($A44,[1]Burgiss_Return!$B:$P,MATCH(R$2,[1]Burgiss_Return!$B$5:$P$5,0),0) -> -0.0115 | S44: =VLOOKUP($A44,[1]Burgiss_Return!$B:$P,MATCH(S$2,[1]Burgiss_Return!$B$5:$P$5,0),0) -> -0.0115 | T44: =VLOOKUP($A44,[1]Burgiss_Return!$B:$P,MATCH(T$2,[1]Burgiss_Return!$B$5:$P$5,0),0) -> -0.0115 | U44: =VLOOKUP($A44,[1]Burgiss_Return!$B:$P,MATCH(U$2,[1]Burgiss_Return!$B$5:$P$5,0),0) -> -0.0115
A45: 40359 | B45: =VLOOKUP($A45,[1]Burgiss_Return!$B:$P,MATCH(B$2,[1]Burgiss_Return!$B$5:$P$5,0),0) -> 0.0015 | C45: =VLOOKUP($A45,[1]Burgiss_Return!$B:$P,MATCH(C$2,[1]Burgiss_Return!$B$5:$P$5,0),0) -> -0.0011 | D45: =VLOOKUP($A45,[1]Burgiss_Return!$B:$P,MATCH(D$2,[1]Burgiss_Return!$B$5:$P$5,0),0) -> -0.0011 | E45: =VLOOKUP($A45,[1]Burgiss_Return!$B:$P,MATCH(E$2,[1]Burgiss_Return!$B$5:$P$5,0),0) -> 0.0211 | F45: =VLOOKUP($A45,[1]Burgiss_Return!$B:$P,MATCH(F$2,[1]Burgiss_Return!$B$5:$P$5,0),0) -> -0.0104 | G45: =VLOOKUP($A45,[1]Burgiss_Return!$B:$P,MATCH(G$2,[1]Burgiss_Return!$B$5:$P$5,0),0) -> 0.0211 | H45: =VLOOKUP($A45,[1]Burgiss_Return!$B:$P,MATCH(H$2,[1]Burgiss_Return!$B$5:$P$5,0),0) -> -0.0188 | I45: =VLOOKUP($A45,[1]Burgiss_Return!$B:$P,MATCH(I$2,[1]Burgiss_Return!$B$5:$P$5,0),0) -> -0.0172 | J45: =VLOOKUP($A45,[1]Burgiss_Return!$B:$P,MATCH(J$2,[1]Burgiss_Return!$B$5:$P$5,0),0) -> 0.0114 | K45: -0.015008741 | L45: 0.002125 | M45: =VLOOKUP($A45,[1]Burgiss_Return!$B:$P,MATCH(M$2,[1]Burgiss_Return!$B$5:$P$5,0),0) -> 0.0343 | N45: 0.002125 | Q45: -0.078864089 | R45: =VLOOKUP($A45,[1]Burgiss_Return!$B:$P,MATCH(R$2,[1]Burgiss_Return!$B$5:$P$5,0),0) -> -0.0019 | S45: =VLOOKUP($A45,[1]Burgiss_Return!$B:$P,MATCH(S$2,[1]Burgiss_Return!$B$5:$P$5,0),0) -> -0.0019 | T45: =VLOOKUP($A45,[1]Burgiss_Return!$B:$P,MATCH(T$2,[1]Burgiss_Return!$B$5:$P$5,0),0) -> -0.0019 | U45: =VLOOKUP($A45,[1]Burgiss_Return!$B:$P,MATCH(U$2,[1]Burgiss_Return!$B$5:$P$5,0),0) -> -0.0019 | V45: 0.04366506
A46: 40451 | B46: =VLOOKUP($A46,[1]Burgiss_Return!$B:$P,MATCH(B$2,[1]Burgiss_Return!$B$5:$P$5,0),0) -> 0.0689 | C46: =VLOOKUP($A46,[1]Burgiss_Return!$B:$P,MATCH(C$2,[1]Burgiss_Return!$B$5:$P$5,0),0) -> 0.0408 | D46: =VLOOKUP($A46,[1]Burgiss_Return!$B:$P,MATCH(D$2,[1]Burgiss_Return!$B$5:$P$5,0),0) -> 0.0408 | E46: =VLOOKUP($A46,[1]Burgiss_Return!$B:$P,MATCH(E$2,[1]Burgiss_Return!$B$5:$P$5,0),0) -> 0.0613 | F46: =VLOOKUP($A46,[1]Burgiss_Return!$B:$P,MATCH(F$2,[1]Burgiss_Return!$B$5:$P$5,0),0) -> 0.0662 | G46: =VLOOKUP($A46,[1]Burgiss_Return!$B:$P,MATCH(G$2,[1]Burgiss_Return!$B$5:$P$5,0),0) -> 0.0613 | H46: =VLOOKUP($A46,[1]Burgiss_Return!$B:$P,MATCH(H$2,[1]Burgiss_Return!$B$5:$P$5,0),0) -> 0.0638 | I46: =VLOOKUP($A46,[1]Burgiss_Return!$B:$P,MATCH(I$2,[1]Burgiss_Return!$B$5:$P$5,0),0) -> 0.0502 | J46: =VLOOKUP($A46,[1]Burgiss_Return!$B:$P,MATCH(J$2,[1]Burgiss_Return!$B$5:$P$5,0),0) -> 0.1076 | K46: 0.022504337 | L46: 0.092945 | M46: =VLOOKUP($A46,[1]Burgiss_Return!$B:$P,MATCH(M$2,[1]Burgiss_Return!$B$5:$P$5,0),0) -> 0.0559 | N46: 0.092945 | Q46: 0.18440763 | R46: =VLOOKUP($A46,[1]Burgiss_Return!$B:$P,MATCH(R$2,[1]Burgiss_Return!$B$5:$P$5,0),0) -> 0.0878 | S46: =VLOOKUP($A46,[1]Burgiss_Return!$B:$P,MATCH(S$2,[1]Burgiss_Return!$B$5:$P$5,0),0) -> 0.0878 | T46: =VLOOKUP($A46,[1]Burgiss_Return!$B:$P,MATCH(T$2,[1]Burgiss_Return!$B$5:$P$5,0),0) -> 0.0878 | U46: =VLOOKUP($A46,[1]Burgiss_Return!$B:$P,MATCH(U$2,[1]Burgiss_Return!$B$5:$P$5,0),0) -> 0.0878 | V46: 0.042870227
A47: 40543 | B47: =VLOOKUP($A47,[1]Burgiss_Return!$B:$P,MATCH(B$2,[1]Burgiss_Return!$B$5:$P$5,0),0) -> 0.0755 | C47: =VLOOKUP($A47,[1]Burgiss_Return!$B:$P,MATCH(C$2,[1]Burgiss_Return!$B$5:$P$5,0),0) -> 0.0836 | D47: =VLOOKUP($A47,[1]Burgiss_Return!$B:$P,MATCH(D$2,[1]Burgiss_Return!$B$5:$P$5,0),0) -> 0.0836 | E47: =VLOOKUP($A47,[1]Burgiss_Return!$B:$P,MATCH(E$2,[1]Burgiss_Return!$B$5:$P$5,0),0) -> 0.0985 | F47: =VLOOKUP($A47,[1]Burgiss_Return!$B:$P,MATCH(F$2,[1]Burgiss_Return!$B$5:$P$5,0),0) -> 0.0743 | G47: =VLOOKUP($A47,[1]Burgiss_Return!$B:$P,MATCH(G$2,[1]Burgiss_Return!$B$5:$P$5,0),0) -> 0.0985 | H47: =VLOOKUP($A47,[1]Burgiss_Return!$B:$P,MATCH(H$2,[1]Burgiss_Return!$B$5:$P$5,0),0) -> 0.0423 | I47: =VLOOKUP($A47,[1]Burgiss_Return!$B:$P,MATCH(I$2,[1]Burgiss_Return!$B$5:$P$5,0),0) -> 0.0609 | J47: =VLOOKUP($A47,[1]Burgiss_Return!$B:$P,MATCH(J$2,[1]Burgiss_Return!$B$5:$P$5,0),0) -> 0.1137 | K47: 0.025828557 | L47: 0.04757 | M47: =VLOOKUP($A47,[1]Burgiss_Return!$B:$P,MATCH(M$2,[1]Burgiss_Return!$B$5:$P$5,0),0) -> 0.0841 | N47: 0.04757 | Q47: 0.06151272 | R47: =VLOOKUP($A47,[1]Burgiss_Return!$B:$P,MATCH(R$2,[1]Burgiss_Return!$B$5:$P$5,0),0) -> 0.016 | S47: =VLOOKUP($A47,[1]Burgiss_Return!$B:$P,MATCH(S$2,[1]Burgiss_Return!$B$5:$P$5,0),0) -> 0.016 | T47: =VLOOKUP($A47,[1]Burgiss_Return!$B:$P,MATCH(T$2,[1]Burgiss_Return!$B$5:$P$5,0),0) -> 0.016 | U47: =VLOOKUP($A47,[1]Burgiss_Return!$B:$P,MATCH(U$2,[1]Burgiss_Return!$B$5:$P$5,0),0) -> 0.016 | V47: -0.016424757
A48: 40633 | B48: =VLOOKUP($A48,[1]Burgiss_Return!$B:$P,MATCH(B$2,[1]Burgiss_Return!$B$5:$P$5,0),0) -> 0.0625 | C48: =VLOOKUP($A48,[1]Burgiss_Return!$B:$P,MATCH(C$2,[1]Burgiss_Return!$B$5:$P$5,0),0) -> 0.0341 | D48: =VLOOKUP($A48,[1]Burgiss_Return!$B:$P,MATCH(D$2,[1]Burgiss_Return!$B$5:$P$5,0),0) -> 0.0341 | E48: =VLOOKUP($A48,[1]Burgiss_Return!$B:$P,MATCH(E$2,[1]Burgiss_Return!$B$5:$P$5,0),0) -> 0.0421 | F48: =VLOOKUP($A48,[1]Burgiss_Return!$B:$P,MATCH(F$2,[1]Burgiss_Return!$B$5:$P$5,0),0) -> 0.0479 | G48: =VLOOKUP($A48,[1]Burgiss_Return!$B:$P,MATCH(G$2,[1]Burgiss_Return!$B$5:$P$5,0),0) -> 0.0421 | H48: =VLOOKUP($A48,[1]Burgiss_Return!$B:$P,MATCH(H$2,[1]Burgiss_Return!$B$5:$P$5,0),0) -> 0.0261 | I48: =VLOOKUP($A48,[1]Burgiss_Return!$B:$P,MATCH(I$2,[1]Burgiss_Return!$B$5:$P$5,0),0) -> 0.051 | J48: =VLOOKUP($A48,[1]Burgiss_Return!$B:$P,MATCH(J$2,[1]Burgiss_Return!$B$5:$P$5,0),0) -> 0.013 | K48: 0.010905277 | L48: 0.041149 | M48: =VLOOKUP($A48,[1]Burgiss_Return!$B:$P,MATCH(M$2,[1]Burgiss_Return!$B$5:$P$5,0),0) -> 0.0495 | N48: 0.041149 | Q48: 0.030433286 | R48: =VLOOKUP($A48,[1]Burgiss_Return!$B:$P,MATCH(R$2,[1]Burgiss_Return!$B$5:$P$5,0),0) -> 0.0587 | S48: =VLOOKUP($A48,[1]Burgiss_Return!$B:$P,MATCH(S$2,[1]Burgiss_Return!$B$5:$P$5,0),0) -> 0.0587 | T48: =VLOOKUP($A48,[1]Burgiss_Return!$B:$P,MATCH(T$2,[1]Burgiss_Return!$B$5:$P$5,0),0) -> 0.0587 | U48: =VLOOKUP($A48,[1]Burgiss_Return!$B:$P,MATCH(U$2,[1]Burgiss_Return!$B$5:$P$5,0),0) -> 0.0587 | V48: 0.011567278
A49: 40724 | B49: =VLOOKUP($A49,[1]Burgiss_Return!$B:$P,MATCH(B$2,[1]Burgiss_Return!$B$5:$P$5,0),0) -> 0.0563 | C49: =VLOOKUP($A49,[1]Burgiss_Return!$B:$P,MATCH(C$2,[1]Burgiss_Return!$B$5:$P$5,0),0) -> 0.0697 | D49: =VLOOKUP($A49,[1]Burgiss_Return!$B:$P,MATCH(D$2,[1]Burgiss_Return!$B$5:$P$5,0),0) -> 0.0697 | E49: =VLOOKUP($A49,[1]Burgiss_Return!$B:$P,MATCH(E$2,[1]Burgiss_Return!$B$5:$P$5,0),0) -> 0.0458 | F49: =VLOOKUP($A49,[1]Burgiss_Return!$B:$P,MATCH(F$2,[1]Burgiss_Return!$B$5:$P$5,0),0) -> 0.0489 | G49: =VLOOKUP($A49,[1]Burgiss_Return!$B:$P,MATCH(G$2,[1]Burgiss_Return!$B$5:$P$5,0),0) -> 0.0458 | H49: =VLOOKUP($A49,[1]Burgiss_Return!$B:$P,MATCH(H$2,[1]Burgiss_Return!$B$5:$P$5,0),0) -> 0.009 | I49: =VLOOKUP($A49,[1]Burgiss_Return!$B:$P,MATCH(I$2,[1]Burgiss_Return!$B$5:$P$5,0),0) -> 0.009 | J49: =VLOOKUP($A49,[1]Burgiss_Return!$B:$P,MATCH(J$2,[1]Burgiss_Return!$B$5:$P$5,0),0) -> 0.0136 | K49: -0.0077328523 | L49: 0.04277 | M49: =VLOOKUP($A49,[1]Burgiss_Return!$B:$P,MATCH(M$2,[1]Burgiss_Return!$B$5:$P$5,0),0) -> 0.0513 | N49: 0.04277 | Q49: 0.0294209 | R49: =VLOOKUP($A49,[1]Burgiss_Return!$B:$P,MATCH(R$2,[1]Burgiss_Return!$B$5:$P$5,0),0) -> 0.0314 | S49: =VLOOKUP($A49,[1]Burgiss_Return!$B:$P,MATCH(S$2,[1]Burgiss_Return!$B$5:$P$5,0),0) -> 0.0314 | T49: =VLOOKUP($A49,[1]Burgiss_Return!$B:$P,MATCH(T$2,[1]Burgiss_Return!$B$5:$P$5,0),0) -> 0.0314 | U49: =VLOOKUP($A49,[1]Burgiss_Return!$B:$P,MATCH(U$2,[1]Burgiss_Return!$B$5:$P$5,0),0) -> 0.0314 | V49: 0.028091125
A50: 40816 | B50: =VLOOKUP($A50,[1]Burgiss_Return!$B:$P,MATCH(B$2,[1]Burgiss_Return!$B$5:$P$5,0),0) -> -0.0642 | C50: =VLOOKUP($A50,[1]Burgiss_Return!$B:$P,MATCH(C$2,[1]Burgiss_Return!$B$5:$P$5,0),0) -> -0.0061 | D50: =VLOOKUP($A50,[1]Burgiss_Return!$B:$P,MATCH(D$2,[1]Burgiss_Return!$B$5:$P$5,0),0) -> -0.0061 | E50: =VLOOKUP($A50,[1]Burgiss_Return!$B:$P,MATCH(E$2,[1]Burgiss_Return!$B$5:$P$5,0),0) -> 0.0115 | F50: =VLOOKUP($A50,[1]Burgiss_Return!$B:$P,MATCH(F$2,[1]Burgiss_Return!$B$5:$P$5,0),0) -> -0.0266 | G50: =VLOOKUP($A50,[1]Burgiss_Return!$B:$P,MATCH(G$2,[1]Burgiss_Return!$B$5:$P$5,0),0) -> 0.0115 | H50: =VLOOKUP($A50,[1]Burgiss_Return!$B:$P,MATCH(H$2,[1]Burgiss_Return!$B$5:$P$5,0),0) -> -0.0718 | I50: =VLOOKUP($A50,[1]Burgiss_Return!$B:$P,MATCH(I$2,[1]Burgiss_Return!$B$5:$P$5,0),0) -> -0.1002 | J50: =VLOOKUP($A50,[1]Burgiss_Return!$B:$P,MATCH(J$2,[1]Burgiss_Return!$B$5:$P$5,0),0) -> -0.0703 | K50: -0.039074656 | L50: -0.008094 | M50: =VLOOKUP($A50,[1]Burgiss_Return!$B:$P,MATCH(M$2,[1]Burgiss_Return!$B$5:$P$5,0),0) -> 0.0035 | N50: -0.008094 | Q50: -0.17301166 | R50: =VLOOKUP($A50,[1]Burgiss_Return!$B:$P,MATCH(R$2,[1]Burgiss_Return!$B$5:$P$5,0),0) -> -0.1074 | S50: =VLOOKUP($A50,[1]Burgiss_Return!$B:$P,MATCH(S$2,[1]Burgiss_Return!$B$5:$P$5,0),0) -> -0.1074 | T50: =VLOOKUP($A50,[1]Burgiss_Return!$B:$P,MATCH(T$2,[1]Burgiss_Return!$B$5:$P$5,0),0) -> -0.1074 | U50: =VLOOKUP($A50,[1]Burgiss_Return!$B:$P,MATCH(U$2,[1]Burgiss_Return!$B$5:$P$5,0),0) -> -0.1074 | V50: 0.054654349
A51: 40908 | B51: =VLOOKUP($A51,[1]Burgiss_Return!$B:$P,MATCH(B$2,[1]Burgiss_Return!$B$5:$P$5,0),0) -> 0.0355 | C51: =VLOOKUP($A51,[1]Burgiss_Return!$B:$P,MATCH(C$2,[1]Burgiss_Return!$B$5:$P$5,0),0) -> 0.0264 | D51: =VLOOKUP($A51,[1]Burgiss_Return!$B:$P,MATCH(D$2,[1]Burgiss_Return!$B$5:$P$5,0),0) -> 0.0264 | E51: =VLOOKUP($A51,[1]Burgiss_Return!$B:$P,MATCH(E$2,[1]Burgiss_Return!$B$5:$P$5,0),0) -> 0.0197 | F51: =VLOOKUP($A51,[1]Burgiss_Return!$B:$P,MATCH(F$2,[1]Burgiss_Return!$B$5:$P$5,0),0) -> 0.0132 | G51: =VLOOKUP($A51,[1]Burgiss_Return!$B:$P,MATCH(G$2,[1]Burgiss_Return!$B$5:$P$5,0),0) -> 0.0197 | H51: =VLOOKUP($A51,[1]Burgiss_Return!$B:$P,MATCH(H$2,[1]Burgiss_Return!$B$5:$P$5,0),0) -> 0.0463 | I51: =VLOOKUP($A51,[1]Burgiss_Return!$B:$P,MATCH(I$2,[1]Burgiss_Return!$B$5:$P$5,0),0) -> 0.0358 | J51: =VLOOKUP($A51,[1]Burgiss_Return!$B:$P,MATCH(J$2,[1]Burgiss_Return!$B$5:$P$5,0),0) -> 0.0047 | K51: 0.00058166589 | L51: 0.032949 | M51: =VLOOKUP($A51,[1]Burgiss_Return!$B:$P,MATCH(M$2,[1]Burgiss_Return!$B$5:$P$5,0),0) -> 0.0379 | N51: 0.032949 | Q51: 0.07363003 | R51: =VLOOKUP($A51,[1]Burgiss_Return!$B:$P,MATCH(R$2,[1]Burgiss_Return!$B$5:$P$5,0),0) -> 0.0137 | S51: =VLOOKUP($A51,[1]Burgiss_Return!$B:$P,MATCH(S$2,[1]Burgiss_Return!$B$5:$P$5,0),0) -> 0.0137 | T51: =VLOOKUP($A51,[1]Burgiss_Return!$B:$P,MATCH(T$2,[1]Burgiss_Return!$B$5:$P$5,0),0) -> 0.0137 | U51: =VLOOKUP($A51,[1]Burgiss_Return!$B:$P,MATCH(U$2,[1]Burgiss_Return!$B$5:$P$5,0),0) -> 0.0137 | V51: 0.025498018
A52: 40999 | B52: =VLOOKUP($A52,[1]Burgiss_Return!$B:$P,MATCH(B$2,[1]Burgiss_Return!$B$5:$P$5,0),0) -> 0.0624 | C52: =VLOOKUP($A52,[1]Burgiss_Return!$B:$P,MATCH(C$2,[1]Burgiss_Return!$B$5:$P$5,0),0) -> 0.0508 | D52: =VLOOKUP($A52,[1]Burgiss_Return!$B:$P,MATCH(D$2,[1]Burgiss_Return!$B$5:$P$5,0),0) -> 0.0508 | E52: =VLOOKUP($A52,[1]Burgiss_Return!$B:$P,MATCH(E$2,[1]Burgiss_Return!$B$5:$P$5,0),0) -> 0.0261 | F52: =VLOOKUP($A52,[1]Burgiss_Return!$B:$P,MATCH(F$2,[1]Burgiss_Return!$B$5:$P$5,0),0) -> 0.039 | G52: =VLOOKUP($A52,[1]Burgiss_Return!$B:$P,MATCH(G$2,[1]Burgiss_Return!$B$5:$P$5,0),0) -> 0.0261 | H52: =VLOOKUP($A52,[1]Burgiss_Return!$B:$P,MATCH(H$2,[1]Burgiss_Return!$B$5:$P$5,0),0) -> 0.0584 | I52: =VLOOKUP($A52,[1]Burgiss_Return!$B:$P,MATCH(I$2,[1]Burgiss_Return!$B$5:$P$5,0),0) -> 0.0726 | J52: =VLOOKUP($A52,[1]Burgiss_Return!$B:$P,MATCH(J$2,[1]Burgiss_Return!$B$5:$P$5,0),0) -> 0.049 | K52: 0.024743051 | L52: 0.030824 | M52: =VLOOKUP($A52,[1]Burgiss_Return!$B:$P,MATCH(M$2,[1]Burgiss_Return!$B$5:$P$5,0),0) -> 0.0229 | N52: 0.030824 | O52: 0.007289 | P52: 0.0171654 | Q52: 0.12897202 | R52: =VLOOKUP($A52,[1]Burgiss_Return!$B:$P,MATCH(R$2,[1]Burgiss_Return!$B$5:$P$5,0),0) -> 0.0877 | S52: =VLOOKUP($A52,[1]Burgiss_Return!$B:$P,MATCH(S$2,[1]Burgiss_Return!$B$5:$P$5,0),0) -> 0.0877 | T52: =VLOOKUP($A52,[1]Burgiss_Return!$B:$P,MATCH(T$2,[1]Burgiss_Return!$B$5:$P$5,0),0) -> 0.0877 | U52: =VLOOKUP($A52,[1]Burgiss_Return!$B:$P,MATCH(U$2,[1]Burgiss_Return!$B$5:$P$5,0),0) -> 0.0877 | V52: 0.0048578104
A53: 41090 | B53: =VLOOKUP($A53,[1]Burgiss_Return!$B:$P,MATCH(B$2,[1]Burgiss_Return!$B$5:$P$5,0),0) -> -0.0027 | C53: =VLOOKUP($A53,[1]Burgiss_Return!$B:$P,MATCH(C$2,[1]Burgiss_Return!$B$5:$P$5,0),0) -> -0.001 | D53: =VLOOKUP($A53,[1]Burgiss_Return!$B:$P,MATCH(D$2,[1]Burgiss_Return!$B$5:$P$5,0),0) -> -0.001 | E53: =VLOOKUP($A53,[1]Burgiss_Return!$B:$P,MATCH(E$2,[1]Burgiss_Return!$B$5:$P$5,0),0) -> 0.0196 | F53: =VLOOKUP($A53,[1]Burgiss_Return!$B:$P,MATCH(F$2,[1]Burgiss_Return!$B$5:$P$5,0),0) -> 0.004 | G53: =VLOOKUP($A53,[1]Burgiss_Return!$B:$P,MATCH(G$2,[1]Burgiss_Return!$B$5:$P$5,0),0) -> 0.0196 | H53: =VLOOKUP($A53,[1]Burgiss_Return!$B:$P,MATCH(H$2,[1]Burgiss_Return!$B$5:$P$5,0),0) -> 0.004 | I53: =VLOOKUP($A53,[1]Burgiss_Return!$B:$P,MATCH(I$2,[1]Burgiss_Return!$B$5:$P$5,0),0) -> 0.0059 | J53: =VLOOKUP($A53,[1]Burgiss_Return!$B:$P,MATCH(J$2,[1]Burgiss_Return!$B$5:$P$5,0),0) -> -0.0216 | K53: -0.017289388 | L53: 0.009094 | M53: =VLOOKUP($A53,[1]Burgiss_Return!$B:$P,MATCH(M$2,[1]Burgiss_Return!$B$5:$P$5,0),0) -> 0.0144 | N53: 0.009094 | O53: 0.007421 | P53: 0.0231417 | Q53: 0.021177567 | R53: =VLOOKUP($A53,[1]Burgiss_Return!$B:$P,MATCH(R$2,[1]Burgiss_Return!$B$5:$P$5,0),0) -> -0.0055 | S53: =VLOOKUP($A53,[1]Burgiss_Return!$B:$P,MATCH(S$2,[1]Burgiss_Return!$B$5:$P$5,0),0) -> -0.0055 | T53: =VLOOKUP($A53,[1]Burgiss_Return!$B:$P,MATCH(T$2,[1]Burgiss_Return!$B$5:$P$5,0),0) -> -0.0055 | U53: =VLOOKUP($A53,[1]Burgiss_Return!$B:$P,MATCH(U$2,[1]Burgiss_Return!$B$5:$P$5,0),0) -> -0.0055 | V53: 0.03407877
A54: 41182 | B54: =VLOOKUP($A54,[1]Burgiss_Return!$B:$P,MATCH(B$2,[1]Burgiss_Return!$B$5:$P$5,0),0) -> 0.037 | C54: =VLOOKUP($A54,[1]Burgiss_Return!$B:$P,MATCH(C$2,[1]Burgiss_Return!$B$5:$P$5,0),0) -> 0.008 | D54: =VLOOKUP($A54,[1]Burgiss_Return!$B:$P,MATCH(D$2,[1]Burgiss_Return!$B$5:$P$5,0),0) -> 0.008 | E54: =VLOOKUP($A54,[1]Burgiss_Return!$B:$P,MATCH(E$2,[1]Burgiss_Return!$B$5:$P$5,0),0) -> 0.0267 | F54: =VLOOKUP($A54,[1]Burgiss_Return!$B:$P,MATCH(F$2,[1]Burgiss_Return!$B$5:$P$5,0),0) -> 0.0204 | G54: =VLOOKUP($A54,[1]Burgiss_Return!$B:$P,MATCH(G$2,[1]Burgiss_Return!$B$5:$P$5,0),0) -> 0.0267 | H54: =VLOOKUP($A54,[1]Burgiss_Return!$B:$P,MATCH(H$2,[1]Burgiss_Return!$B$5:$P$5,0),0) -> 0.0648 | I54: =VLOOKUP($A54,[1]Burgiss_Return!$B:$P,MATCH(I$2,[1]Burgiss_Return!$B$5:$P$5,0),0) -> 0.0507 | J54: =VLOOKUP($A54,[1]Burgiss_Return!$B:$P,MATCH(J$2,[1]Burgiss_Return!$B$5:$P$5,0),0) -> 0.0354 | K54: 0.018153294 | L54: 0.027383 | M54: =VLOOKUP($A54,[1]Burgiss_Return!$B:$P,MATCH(M$2,[1]Burgiss_Return!$B$5:$P$5,0),0) -> 0.0238 | N54: 0.027383 | O54: 0.011528 | P54: 0.0177388 | Q54: 0.055058288 | R54: =VLOOKUP($A54,[1]Burgiss_Return!$B:$P,MATCH(R$2,[1]Burgiss_Return!$B$5:$P$5,0),0) -> 0.0306 | S54: =VLOOKUP($A54,[1]Burgiss_Return!$B:$P,MATCH(S$2,[1]Burgiss_Return!$B$5:$P$5,0),0) -> 0.0306 | T54: =VLOOKUP($A54,[1]Burgiss_Return!$B:$P,MATCH(T$2,[1]Burgiss_Return!$B$5:$P$5,0),0) -> 0.0306 | U54: =VLOOKUP($A54,[1]Burgiss_Return!$B:$P,MATCH(U$2,[1]Burgiss_Return!$B$5:$P$5,0),0) -> 0.0306 | V54: 0.04147688
A55: 41274 | B55: =VLOOKUP($A55,[1]Burgiss_Return!$B:$P,MATCH(B$2,[1]Burgiss_Return!$B$5:$P$5,0),0) -> 0.0448 | C55: =VLOOKUP($A55,[1]Burgiss_Return!$B:$P,MATCH(C$2,[1]Burgiss_Return!$B$5:$P$5,0),0) -> 0.031 | D55: =VLOOKUP($A55,[1]Burgiss_Return!$B:$P,MATCH(D$2,[1]Burgiss_Return!$B$5:$P$5,0),0) -> 0.031 | E55: =VLOOKUP($A55,[1]Burgiss_Return!$B:$P,MATCH(E$2,[1]Burgiss_Return!$B$5:$P$5,0),0) -> 0.0476 | F55: =VLOOKUP($A55,[1]Burgiss_Return!$B:$P,MATCH(F$2,[1]Burgiss_Return!$B$5:$P$5,0),0) -> 0.0272 | G55: =VLOOKUP($A55,[1]Burgiss_Return!$B:$P,MATCH(G$2,[1]Burgiss_Return!$B$5:$P$5,0),0) -> 0.0476 | H55: =VLOOKUP($A55,[1]Burgiss_Return!$B:$P,MATCH(H$2,[1]Burgiss_Return!$B$5:$P$5,0),0) -> 0.0163 | I55: =VLOOKUP($A55,[1]Burgiss_Return!$B:$P,MATCH(I$2,[1]Burgiss_Return!$B$5:$P$5,0),0) -> 0.0276 | J55: =VLOOKUP($A55,[1]Burgiss_Return!$B:$P,MATCH(J$2,[1]Burgiss_Return!$B$5:$P$5,0),0) -> 0.0526 | K55: 0.01643341 | L55: 0.018906 | M55: =VLOOKUP($A55,[1]Burgiss_Return!$B:$P,MATCH(M$2,[1]Burgiss_Return!$B$5:$P$5,0),0) -> 0.037 | N55: 0.018906 | O55: 0.019803 | P55: 0.0259903 | Q55: 0.057670643 | R55: =VLOOKUP($A55,[1]Burgiss_Return!$B:$P,MATCH(R$2,[1]Burgiss_Return!$B$5:$P$5,0),0) -> 0.0055 | S55: =VLOOKUP($A55,[1]Burgiss_Return!$B:$P,MATCH(S$2,[1]Burgiss_Return!$B$5:$P$5,0),0) -> 0.0055 | T55: =VLOOKUP($A55,[1]Burgiss_Return!$B:$P,MATCH(T$2,[1]Burgiss_Return!$B$5:$P$5,0),0) -> 0.0055 | U55: =VLOOKUP($A55,[1]Burgiss_Return!$B:$P,MATCH(U$2,[1]Burgiss_Return!$B$5:$P$5,0),0) -> 0.0055 | V55: 0.011544231
A56: 41364 | B56: =VLOOKUP($A56,[1]Burgiss_Return!$B:$P,MATCH(B$2,[1]Burgiss_Return!$B$5:$P$5,0),0) -> 0.0302 | C56: =VLOOKUP($A56,[1]Burgiss_Return!$B:$P,MATCH(C$2,[1]Burgiss_Return!$B$5:$P$5,0),0) -> 0.0373 | D56: =VLOOKUP($A56,[1]Burgiss_Return!$B:$P,MATCH(D$2,[1]Burgiss_Return!$B$5:$P$5,0),0) -> 0.0373 | E56: =VLOOKUP($A56,[1]Burgiss_Return!$B:$P,MATCH(E$2,[1]Burgiss_Return!$B$5:$P$5,0),0) -> 0.0093 | F56: =VLOOKUP($A56,[1]Burgiss_Return!$B:$P,MATCH(F$2,[1]Burgiss_Return!$B$5:$P$5,0),0) -> 0.0157 | G56: =VLOOKUP($A56,[1]Burgiss_Return!$B:$P,MATCH(G$2,[1]Burgiss_Return!$B$5:$P$5,0),0) -> 0.0093 | H56: =VLOOKUP($A56,[1]Burgiss_Return!$B:$P,MATCH(H$2,[1]Burgiss_Return!$B$5:$P$5,0),0) -> 0.0076 | I56: =VLOOKUP($A56,[1]Burgiss_Return!$B:$P,MATCH(I$2,[1]Burgiss_Return!$B$5:$P$5,0),0) -> 0.0546 | J56: =VLOOKUP($A56,[1]Burgiss_Return!$B:$P,MATCH(J$2,[1]Burgiss_Return!$B$5:$P$5,0),0) -> 0.0346 | K56: 0.027713703 | L56: 0.008924 | M56: =VLOOKUP($A56,[1]Burgiss_Return!$B:$P,MATCH(M$2,[1]Burgiss_Return!$B$5:$P$5,0),0) -> 0.0218 | N56: 0.008924 | O56: 0.018125 | P56: 0.0258241 | Q56: 0.062609708 | R56: =VLOOKUP($A56,[1]Burgiss_Return!$B:$P,MATCH(R$2,[1]Burgiss_Return!$B$5:$P$5,0),0) -> -0.0163 | S56: =VLOOKUP($A56,[1]Burgiss_Return!$B:$P,MATCH(S$2,[1]Burgiss_Return!$B$5:$P$5,0),0) -> -0.0163 | T56: =VLOOKUP($A56,[1]Burgiss_Return!$B:$P,MATCH(T$2,[1]Burgiss_Return!$B$5:$P$5,0),0) -> -0.0163 | U56: =VLOOKUP($A56,[1]Burgiss_Return!$B:$P,MATCH(U$2,[1]Burgiss_Return!$B$5:$P$5,0),0) -> -0.0163 | V56: -0.0035931002
A57: 41455 | B57: =VLOOKUP($A57,[1]Burgiss_Return!$B:$P,MATCH(B$2,[1]Burgiss_Return!$B$5:$P$5,0),0) -> 0.0351 | C57: =VLOOKUP($A57,[1]Burgiss_Return!$B:$P,MATCH(C$2,[1]Burgiss_Return!$B$5:$P$5,0),0) -> 0.0484 | D57: =VLOOKUP($A57,[1]Burgiss_Return!$B:$P,MATCH(D$2,[1]Burgiss_Return!$B$5:$P$5,0),0) -> 0.0484 | E57: =VLOOKUP($A57,[1]Burgiss_Return!$B:$P,MATCH(E$2,[1]Burgiss_Return!$B$5:$P$5,0),0) -> 0.0229 | F57: =VLOOKUP($A57,[1]Burgiss_Return!$B:$P,MATCH(F$2,[1]Burgiss_Return!$B$5:$P$5,0),0) -> 0.0196 | G57: =VLOOKUP($A57,[1]Burgiss_Return!$B:$P,MATCH(G$2,[1]Burgiss_Return!$B$5:$P$5,0),0) -> 0.0229 | H57: =VLOOKUP($A57,[1]Burgiss_Return!$B:$P,MATCH(H$2,[1]Burgiss_Return!$B$5:$P$5,0),0) -> 0.0034 | I57: =VLOOKUP($A57,[1]Burgiss_Return!$B:$P,MATCH(I$2,[1]Burgiss_Return!$B$5:$P$5,0),0) -> 0.0276 | J57: =VLOOKUP($A57,[1]Burgiss_Return!$B:$P,MATCH(J$2,[1]Burgiss_Return!$B$5:$P$5,0),0) -> -0.0152 | K57: 0.0080896705 | L57: 0.000813 | M57: =VLOOKUP($A57,[1]Burgiss_Return!$B:$P,MATCH(M$2,[1]Burgiss_Return!$B$5:$P$5,0),0) -> 0.0341 | N57: 0.000813 | O57: -0.01201 | P57: 0.0193642 | Q57: -0.036299995 | R57: =VLOOKUP($A57,[1]Burgiss_Return!$B:$P,MATCH(R$2,[1]Burgiss_Return!$B$5:$P$5,0),0) -> 0.0321 | S57: =VLOOKUP($A57,[1]Burgiss_Return!$B:$P,MATCH(S$2,[1]Burgiss_Return!$B$5:$P$5,0),0) -> 0.0321 | T57: =VLOOKUP($A57,[1]Burgiss_Return!$B:$P,MATCH(T$2,[1]Burgiss_Return!$B$5:$P$5,0),0) -> 0.0321 | U57: =VLOOKUP($A57,[1]Burgiss_Return!$B:$P,MATCH(U$2,[1]Burgiss_Return!$B$5:$P$5,0),0) -> 0.0321 | V57: -0.040117481
A58: 41547 | B58: =VLOOKUP($A58,[1]Burgiss_Return!$B:$P,MATCH(B$2,[1]Burgiss_Return!$B$5:$P$5,0),0) -> 0.0566 | C58: =VLOOKUP($A58,[1]Burgiss_Return!$B:$P,MATCH(C$2,[1]Burgiss_Return!$B$5:$P$5,0),0) -> 0.0861 | D58: =VLOOKUP($A58,[1]Burgiss_Return!$B:$P,MATCH(D$2,[1]Burgiss_Return!$B$5:$P$5,0),0) -> 0.0861 | E58: =VLOOKUP($A58,[1]Burgiss_Return!$B:$P,MATCH(E$2,[1]Burgiss_Return!$B$5:$P$5,0),0) -> 0.0373 | F58: =VLOOKUP($A58,[1]Burgiss_Return!$B:$P,MATCH(F$2,[1]Burgiss_Return!$B$5:$P$5,0),0) -> 0.0446 | G58: =VLOOKUP($A58,[1]Burgiss_Return!$B:$P,MATCH(G$2,[1]Burgiss_Return!$B$5:$P$5,0),0) -> 0.0373 | H58: =VLOOKUP($A58,[1]Burgiss_Return!$B:$P,MATCH(H$2,[1]Burgiss_Return!$B$5:$P$5,0),0) -> 0.0406 | I58: =VLOOKUP($A58,[1]Burgiss_Return!$B:$P,MATCH(I$2,[1]Burgiss_Return!$B$5:$P$5,0),0) -> 0.0344 | J58: =VLOOKUP($A58,[1]Burgiss_Return!$B:$P,MATCH(J$2,[1]Burgiss_Return!$B$5:$P$5,0),0) -> 0.0345 | K58: 0.012347489 | L58: 0.045818 | M58: =VLOOKUP($A58,[1]Burgiss_Return!$B:$P,MATCH(M$2,[1]Burgiss_Return!$B$5:$P$5,0),0) -> 0.0343 | N58: 0.045818 | O58: 0.015674 | P58: 0.0047014 | Q58: 0.024399451 | R58: =VLOOKUP($A58,[1]Burgiss_Return!$B:$P,MATCH(R$2,[1]Burgiss_Return!$B$5:$P$5,0),0) -> 0.0528 | S58: =VLOOKUP($A58,[1]Burgiss_Return!$B:$P,MATCH(S$2,[1]Burgiss_Return!$B$5:$P$5,0),0) -> 0.0528 | T58: =VLOOKUP($A58,[1]Burgiss_Return!$B:$P,MATCH(T$2,[1]Burgiss_Return!$B$5:$P$5,0),0) -> 0.0528 | U58: =VLOOKUP($A58,[1]Burgiss_Return!$B:$P,MATCH(U$2,[1]Burgiss_Return!$B$5:$P$5,0),0) -> 0.0528 | V58: 0.00037035212
A59: 41639 | B59: =VLOOKUP($A59,[1]Burgiss_Return!$B:$P,MATCH(B$2,[1]Burgiss_Return!$B$5:$P$5,0),0) -> 0.0717 | C59: =VLOOKUP($A59,[1]Burgiss_Return!$B:$P,MATCH(C$2,[1]Burgiss_Return!$B$5:$P$5,0),0) -> 0.0993 | D59: =VLOOKUP($A59,[1]Burgiss_Return!$B:$P,MATCH(D$2,[1]Burgiss_Return!$B$5:$P$5,0),0) -> 0.0993 | E59: =VLOOKUP($A59,[1]Burgiss_Return!$B:$P,MATCH(E$2,[1]Burgiss_Return!$B$5:$P$5,0),0) -> 0.0742 | F59: =VLOOKUP($A59,[1]Burgiss_Return!$B:$P,MATCH(F$2,[1]Burgiss_Return!$B$5:$P$5,0),0) -> 0.0724 | G59: =VLOOKUP($A59,[1]Burgiss_Return!$B:$P,MATCH(G$2,[1]Burgiss_Return!$B$5:$P$5,0),0) -> 0.0742 | H59: =VLOOKUP($A59,[1]Burgiss_Return!$B:$P,MATCH(H$2,[1]Burgiss_Return!$B$5:$P$5,0),0) -> 0.0285 | I59: =VLOOKUP($A59,[1]Burgiss_Return!$B:$P,MATCH(I$2,[1]Burgiss_Return!$B$5:$P$5,0),0) -> 0.0451 | J59: =VLOOKUP($A59,[1]Burgiss_Return!$B:$P,MATCH(J$2,[1]Burgiss_Return!$B$5:$P$5,0),0) -> 0.0949 | K59: 0.026833715 | L59: 0.024718 | M59: =VLOOKUP($A59,[1]Burgiss_Return!$B:$P,MATCH(M$2,[1]Burgiss_Return!$B$5:$P$5,0),0) -> 0.0727 | N59: 0.024718 | O59: 0.006925 | P59: 0.0344505 | Q59: -0.0048931916 | R59: =VLOOKUP($A59,[1]Burgiss_Return!$B:$P,MATCH(R$2,[1]Burgiss_Return!$B$5:$P$5,0),0) -> 0.0441 | S59: =VLOOKUP($A59,[1]Burgiss_Return!$B:$P,MATCH(S$2,[1]Burgiss_Return!$B$5:$P$5,0),0) -> 0.0441 | T59: =VLOOKUP($A59,[1]Burgiss_Return!$B:$P,MATCH(T$2,[1]Burgiss_Return!$B$5:$P$5,0),0) -> 0.0441 | U59: =VLOOKUP($A59,[1]Burgiss_Return!$B:$P,MATCH(U$2,[1]Burgiss_Return!$B$5:$P$5,0),0) -> 0.0441 | V59: 0.015046936
A60: 41729 | B60: =VLOOKUP($A60,[1]Burgiss_Return!$B:$P,MATCH(B$2,[1]Burgiss_Return!$B$5:$P$5,0),0) -> 0.0339 | C60: =VLOOKUP($A60,[1]Burgiss_Return!$B:$P,MATCH(C$2,[1]Burgiss_Return!$B$5:$P$5,0),0) -> 0.0359 | D60: =VLOOKUP($A60,[1]Burgiss_Return!$B:$P,MATCH(D$2,[1]Burgiss_Return!$B$5:$P$5,0),0) -> 0.0359 | E60: =VLOOKUP($A60,[1]Burgiss_Return!$B:$P,MATCH(E$2,[1]Burgiss_Return!$B$5:$P$5,0),0) -> 0.0212 | F60: =VLOOKUP($A60,[1]Burgiss_Return!$B:$P,MATCH(F$2,[1]Burgiss_Return!$B$5:$P$5,0),0) -> 0.0299 | G60: =VLOOKUP($A60,[1]Burgiss_Return!$B:$P,MATCH(G$2,[1]Burgiss_Return!$B$5:$P$5,0),0) -> 0.0212 | H60: =VLOOKUP($A60,[1]Burgiss_Return!$B:$P,MATCH(H$2,[1]Burgiss_Return!$B$5:$P$5,0),0) -> 0.0293 | I60: =VLOOKUP($A60,[1]Burgiss_Return!$B:$P,MATCH(I$2,[1]Burgiss_Return!$B$5:$P$5,0),0) -> 0.0337 | J60: =VLOOKUP($A60,[1]Burgiss_Return!$B:$P,MATCH(J$2,[1]Burgiss_Return!$B$5:$P$5,0),0) -> 0.0339 | K60: 0.013043425 | L60: 0.032529 | M60: =VLOOKUP($A60,[1]Burgiss_Return!$B:$P,MATCH(M$2,[1]Burgiss_Return!$B$5:$P$5,0),0) -> 0.0249 | N60: 0.032529 | O60: 0.021222 | P60: 0.0250983 | Q60: 0.040144231 | R60: =VLOOKUP($A60,[1]Burgiss_Return!$B:$P,MATCH(R$2,[1]Burgiss_Return!$B$5:$P$5,0),0) -> 0.0346 | S60: =VLOOKUP($A60,[1]Burgiss_Return!$B:$P,MATCH(S$2,[1]Burgiss_Return!$B$5:$P$5,0),0) -> 0.0346 | T60: =VLOOKUP($A60,[1]Burgiss_Return!$B:$P,MATCH(T$2,[1]Burgiss_Return!$B$5:$P$5,0),0) -> 0.0346 | U60: =VLOOKUP($A60,[1]Burgiss_Return!$B:$P,MATCH(U$2,[1]Burgiss_Return!$B$5:$P$5,0),0) -> 0.0346 | V60: 0.039413212
A61: 41820 | B61: =VLOOKUP($A61,[1]Burgiss_Return!$B:$P,MATCH(B$2,[1]Burgiss_Return!$B$5:$P$5,0),0) -> 0.0488 | C61: =VLOOKUP($A61,[1]Burgiss_Return!$B:$P,MATCH(C$2,[1]Burgiss_Return!$B$5:$P$5,0),0) -> 0.0377 | D61: =VLOOKUP($A61,[1]Burgiss_Return!$B:$P,MATCH(D$2,[1]Burgiss_Return!$B$5:$P$5,0),0) -> 0.0377 | E61: =VLOOKUP($A61,[1]Burgiss_Return!$B:$P,MATCH(E$2,[1]Burgiss_Return!$B$5:$P$5,0),0) -> 0.0386 | F61: =VLOOKUP($A61,[1]Burgiss_Return!$B:$P,MATCH(F$2,[1]Burgiss_Return!$B$5:$P$5,0),0) -> 0.0486 | G61: =VLOOKUP($A61,[1]Burgiss_Return!$B:$P,MATCH(G$2,[1]Burgiss_Return!$B$5:$P$5,0),0) -> 0.0386 | H61: =VLOOKUP($A61,[1]Burgiss_Return!$B:$P,MATCH(H$2,[1]Burgiss_Return!$B$5:$P$5,0),0) -> 0.0208 | I61: =VLOOKUP($A61,[1]Burgiss_Return!$B:$P,MATCH(I$2,[1]Burgiss_Return!$B$5:$P$5,0),0) -> 0.0338 | J61: =VLOOKUP($A61,[1]Burgiss_Return!$B:$P,MATCH(J$2,[1]Burgiss_Return!$B$5:$P$5,0),0) -> 0.0437 | K61: 0.013036977 | L61: 0.037198 | M61: =VLOOKUP($A61,[1]Burgiss_Return!$B:$P,MATCH(M$2,[1]Burgiss_Return!$B$5:$P$5,0),0) -> 0.042 | N61: 0.037198 | O61: 0.018332 | P61: 0.0118294 | Q61: 0.078758761 | R61: =VLOOKUP($A61,[1]Burgiss_Return!$B:$P,MATCH(R$2,[1]Burgiss_Return!$B$5:$P$5,0),0) -> 0.0208 | S61: =VLOOKUP($A61,[1]Burgiss_Return!$B:$P,MATCH(S$2,[1]Burgiss_Return!$B$5:$P$5,0),0) -> 0.0208 | T61: =VLOOKUP($A61,[1]Burgiss_Return!$B:$P,MATCH(T$2,[1]Burgiss_Return!$B$5:$P$5,0),0) -> 0.0208 | U61: =VLOOKUP($A61,[1]Burgiss_Return!$B:$P,MATCH(U$2,[1]Burgiss_Return!$B$5:$P$5,0),0) -> 0.0208 | V61: 0.038051995
A62: 41912 | B62: =VLOOKUP($A62,[1]Burgiss_Return!$B:$P,MATCH(B$2,[1]Burgiss_Return!$B$5:$P$5,0),0) -> -0.0088 | C62: =VLOOKUP($A62,[1]Burgiss_Return!$B:$P,MATCH(C$2,[1]Burgiss_Return!$B$5:$P$5,0),0) -> 0.0254 | D62: =VLOOKUP($A62,[1]Burgiss_Return!$B:$P,MATCH(D$2,[1]Burgiss_Return!$B$5:$P$5,0),0) -> 0.0254 | E62: =VLOOKUP($A62,[1]Burgiss_Return!$B:$P,MATCH(E$2,[1]Burgiss_Return!$B$5:$P$5,0),0) -> 0.0129 | F62: =VLOOKUP($A62,[1]Burgiss_Return!$B:$P,MATCH(F$2,[1]Burgiss_Return!$B$5:$P$5,0),0) -> 0.0023 | G62: =VLOOKUP($A62,[1]Burgiss_Return!$B:$P,MATCH(G$2,[1]Burgiss_Return!$B$5:$P$5,0),0) -> 0.0129 | H62: =VLOOKUP($A62,[1]Burgiss_Return!$B:$P,MATCH(H$2,[1]Burgiss_Return!$B$5:$P$5,0),0) -> -0.0071 | I62: =VLOOKUP($A62,[1]Burgiss_Return!$B:$P,MATCH(I$2,[1]Burgiss_Return!$B$5:$P$5,0),0) -> -0.0213 | J62: =VLOOKUP($A62,[1]Burgiss_Return!$B:$P,MATCH(J$2,[1]Burgiss_Return!$B$5:$P$5,0),0) -> 0.0314 | K62: 0.0024596934 | L62: 0.002207 | M62: =VLOOKUP($A62,[1]Burgiss_Return!$B:$P,MATCH(M$2,[1]Burgiss_Return!$B$5:$P$5,0),0) -> 0.0295 | N62: 0.002207 | O62: 0.016005 | P62: 0.0423623 | Q62: -0.044331276 | R62: =VLOOKUP($A62,[1]Burgiss_Return!$B:$P,MATCH(R$2,[1]Burgiss_Return!$B$5:$P$5,0),0) -> -0.0273 | S62: =VLOOKUP($A62,[1]Burgiss_Return!$B:$P,MATCH(S$2,[1]Burgiss_Return!$B$5:$P$5,0),0) -> -0.0273 | T62: =VLOOKUP($A62,[1]Burgiss_Return!$B:$P,MATCH(T$2,[1]Burgiss_Return!$B$5:$P$5,0),0) -> -0.0273 | U62: =VLOOKUP($A62,[1]Burgiss_Return!$B:$P,MATCH(U$2,[1]Burgiss_Return!$B$5:$P$5,0),0) -> -0.0273 | V62: -0.00084581073
A63: 42004 | B63: =VLOOKUP($A63,[1]Burgiss_Return!$B:$P,MATCH(B$2,[1]Burgiss_Return!$B$5:$P$5,0),0) -> 0.0224 | C63: =VLOOKUP($A63,[1]Burgiss_Return!$B:$P,MATCH(C$2,[1]Burgiss_Return!$B$5:$P$5,0),0) -> 0.0789 | D63: =VLOOKUP($A63,[1]Burgiss_Return!$B:$P,MATCH(D$2,[1]Burgiss_Return!$B$5:$P$5,0),0) -> 0.0789 | E63: =VLOOKUP($A63,[1]Burgiss_Return!$B:$P,MATCH(E$2,[1]Burgiss_Return!$B$5:$P$5,0),0) -> 0.025 | F63: =VLOOKUP($A63,[1]Burgiss_Return!$B:$P,MATCH(F$2,[1]Burgiss_Return!$B$5:$P$5,0),0) -> 0.0427 | G63: =VLOOKUP($A63,[1]Burgiss_Return!$B:$P,MATCH(G$2,[1]Burgiss_Return!$B$5:$P$5,0),0) -> 0.025 | H63: =VLOOKUP($A63,[1]Burgiss_Return!$B:$P,MATCH(H$2,[1]Burgiss_Return!$B$5:$P$5,0),0) -> 0.0044 | I63: =VLOOKUP($A63,[1]Burgiss_Return!$B:$P,MATCH(I$2,[1]Burgiss_Return!$B$5:$P$5,0),0) -> -0.0094 | J63: =VLOOKUP($A63,[1]Burgiss_Return!$B:$P,MATCH(J$2,[1]Burgiss_Return!$B$5:$P$5,0),0) -> 0.0438 | K63: 0.0025414869 | L63: 0.009865 | M63: =VLOOKUP($A63,[1]Burgiss_Return!$B:$P,MATCH(M$2,[1]Burgiss_Return!$B$5:$P$5,0),0) -> 0.05 | N63: 0.009865 | O63: 0.016398 | P63: 0.0373498 | Q63: 0.080731577 | R63: =VLOOKUP($A63,[1]Burgiss_Return!$B:$P,MATCH(R$2,[1]Burgiss_Return!$B$5:$P$5,0),0) -> -0.0146 | S63: =VLOOKUP($A63,[1]Burgiss_Return!$B:$P,MATCH(S$2,[1]Burgiss_Return!$B$5:$P$5,0),0) -> -0.0146 | T63: =VLOOKUP($A63,[1]Burgiss_Return!$B:$P,MATCH(T$2,[1]Burgiss_Return!$B$5:$P$5,0),0) -> -0.0146 | U63: =VLOOKUP($A63,[1]Burgiss_Return!$B:$P,MATCH(U$2,[1]Burgiss_Return!$B$5:$P$5,0),0) -> -0.0146 | V63: 0.015424066
... A103: 45657 | B103: =VLOOKUP($A103,[1]Burgiss_Return!$B:$P,MATCH(B$2,[1]Burgiss_Return!$B$5:$P$5,0),0) -> 0.005 | C103: =VLOOKUP($A103,[1]Burgiss_Return!$B:$P,MATCH(C$2,[1]Burgiss_Return!$B$5:$P$5,0),0) -> 0.0402 | D103: =VLOOKUP($A103,[1]Burgiss_Return!$B:$P,MATCH(D$2,[1]Burgiss_Return!$B$5:$P$5,0),0) -> 0.0402 | E103: =VLOOKUP($A103,[1]Burgiss_Return!$B:$P,MATCH(E$2,[1]Burgiss_Return!$B$5:$P$5,0),0) -> 0.0063 | F103: =VLOOKUP($A103,[1]Burgiss_Return!$B:$P,MATCH(F$2,[1]Burgiss_Return!$B$5:$P$5,0),0) -> 0.0042 | G103: =VLOOKUP($A103,[1]Burgiss_Return!$B:$P,MATCH(G$2,[1]Burgiss_Return!$B$5:$P$5,0),0) -> 0.0063 | H103: =VLOOKUP($A103,[1]Burgiss_Return!$B:$P,MATCH(H$2,[1]Burgiss_Return!$B$5:$P$5,0),0) -> -0.004 | I103: =VLOOKUP($A103,[1]Burgiss_Return!$B:$P,MATCH(I$2,[1]Burgiss_Return!$B$5:$P$5,0),0) -> 0.0113 | J103: =VLOOKUP($A103,[1]Burgiss_Return!$B:$P,MATCH(J$2,[1]Burgiss_Return!$B$5:$P$5,0),0) -> -0.0064 | K103: 0.012765312 | L103: 0.007843 | M103: =VLOOKUP($A103,[1]Burgiss_Return!$B:$P,MATCH(M$2,[1]Burgiss_Return!$B$5:$P$5,0),0) -> -0.0239 | N103: 0.007843 | O103: -0.010506 | P103: 0.0292064 | Q103: -0.094520149 | R103: =VLOOKUP($A103,[1]Burgiss_Return!$B:$P,MATCH(R$2,[1]Burgiss_Return!$B$5:$P$5,0),0) -> -0.0314 | S103: =VLOOKUP($A103,[1]Burgiss_Return!$B:$P,MATCH(S$2,[1]Burgiss_Return!$B$5:$P$5,0),0) -> -0.0314 | T103: =VLOOKUP($A103,[1]Burgiss_Return!$B:$P,MATCH(T$2,[1]Burgiss_Return!$B$5:$P$5,0),0) -> -0.0314 | U103: =VLOOKUP($A103,[1]Burgiss_Return!$B:$P,MATCH(U$2,[1]Burgiss_Return!$B$5:$P$5,0),0) -> -0.0314 | V103: -0.029153453
A104: 45747 | B104: =VLOOKUP($A104,[1]Burgiss_Return!$B:$P,MATCH(B$2,[1]Burgiss_Return!$B$5:$P$5,0),0) -> 0.018 | C104: =VLOOKUP($A104,[1]Burgiss_Return!$B:$P,MATCH(C$2,[1]Burgiss_Return!$B$5:$P$5,0),0) -> 0.0333 | D104: =VLOOKUP($A104,[1]Burgiss_Return!$B:$P,MATCH(D$2,[1]Burgiss_Return!$B$5:$P$5,0),0) -> 0.0333 | E104: =VLOOKUP($A104,[1]Burgiss_Return!$B:$P,MATCH(E$2,[1]Burgiss_Return!$B$5:$P$5,0),0) -> 0.0121 | F104: =VLOOKUP($A104,[1]Burgiss_Return!$B:$P,MATCH(F$2,[1]Burgiss_Return!$B$5:$P$5,0),0) -> 0.014 | G104: =VLOOKUP($A104,[1]Burgiss_Return!$B:$P,MATCH(G$2,[1]Burgiss_Return!$B$5:$P$5,0),0) -> 0.0121 | H104: =VLOOKUP($A104,[1]Burgiss_Return!$B:$P,MATCH(H$2,[1]Burgiss_Return!$B$5:$P$5,0),0) -> 0.0317 | I104: =VLOOKUP($A104,[1]Burgiss_Return!$B:$P,MATCH(I$2,[1]Burgiss_Return!$B$5:$P$5,0),0) -> 0.0171 | J104: =VLOOKUP($A104,[1]Burgiss_Return!$B:$P,MATCH(J$2,[1]Burgiss_Return!$B$5:$P$5,0),0) -> 0.016 | K104: 0.0073030262 | M104: =VLOOKUP($A104,[1]Burgiss_Return!$B:$P,MATCH(M$2,[1]Burgiss_Return!$B$5:$P$5,0),0) -> 0.0074 | O104: 0.0323 | P104: 0.0110708 | Q104: 0.018545827 | R104: =VLOOKUP($A104,[1]Burgiss_Return!$B:$P,MATCH(R$2,[1]Burgiss_Return!$B$5:$P$5,0),0) -> 0.0307 | S104: =VLOOKUP($A104,[1]Burgiss_Return!$B:$P,MATCH(S$2,[1]Burgiss_Return!$B$5:$P$5,0),0) -> 0.0307 | T104: =VLOOKUP($A104,[1]Burgiss_Return!$B:$P,MATCH(T$2,[1]Burgiss_Return!$B$5:$P$5,0),0) -> 0.0307 | U104: =VLOOKUP($A104,[1]Burgiss_Return!$B:$P,MATCH(U$2,[1]Burgiss_Return!$B$5:$P$5,0),0) -> 0.0307 | V104: 0.019242912
A105: 45838 | B105: =VLOOKUP($A105,[1]Burgiss_Return!$B:$P,MATCH(B$2,[1]Burgiss_Return!$B$5:$P$5,0),0) -> 0.0432 | C105: =VLOOKUP($A105,[1]Burgiss_Return!$B:$P,MATCH(C$2,[1]Burgiss_Return!$B$5:$P$5,0),0) -> 0.0525 | D105: =VLOOKUP($A105,[1]Burgiss_Return!$B:$P,MATCH(D$2,[1]Burgiss_Return!$B$5:$P$5,0),0) -> 0.0525 | E105: =VLOOKUP($A105,[1]Burgiss_Return!$B:$P,MATCH(E$2,[1]Burgiss_Return!$B$5:$P$5,0),0) -> 0.0273 | F105: =VLOOKUP($A105,[1]Burgiss_Return!$B:$P,MATCH(F$2,[1]Burgiss_Return!$B$5:$P$5,0),0) -> 0.0381 | G105: =VLOOKUP($A105,[1]Burgiss_Return!$B:$P,MATCH(G$2,[1]Burgiss_Return!$B$5:$P$5,0),0) -> 0.0273 | H105: =VLOOKUP($A105,[1]Burgiss_Return!$B:$P,MATCH(H$2,[1]Burgiss_Return!$B$5:$P$5,0),0) -> 0.0372 | I105: =VLOOKUP($A105,[1]Burgiss_Return!$B:$P,MATCH(I$2,[1]Burgiss_Return!$B$5:$P$5,0),0) -> 0.0379 | J105: =VLOOKUP($A105,[1]Burgiss_Return!$B:$P,MATCH(J$2,[1]Burgiss_Return!$B$5:$P$5,0),0) -> 0.0379 | K105: 0.019465085 | M105: =VLOOKUP($A105,[1]Burgiss_Return!$B:$P,MATCH(M$2,[1]Burgiss_Return!$B$5:$P$5,0),0) -> 0.017 | O105: 0.0187 | P105: -0.0013313 | Q105: 0.047196103 | R105: =VLOOKUP($A105,[1]Burgiss_Return!$B:$P,MATCH(R$2,[1]Burgiss_Return!$B$5:$P$5,0),0) -> 0.0819 | S105: =VLOOKUP($A105,[1]Burgiss_Return!$B:$P,MATCH(S$2,[1]Burgiss_Return!$B$5:$P$5,0),0) -> 0.0819 | T105: =VLOOKUP($A105,[1]Burgiss_Return!$B:$P,MATCH(T$2,[1]Burgiss_Return!$B$5:$P$5,0),0) -> 0.0819 | U105: =VLOOKUP($A105,[1]Burgiss_Return!$B:$P,MATCH(U$2,[1]Burgiss_Return!$B$5:$P$5,0),0) -> 0.0819 | V105: 0.016405817
A106: 45930 | B106: =VLOOKUP($A106,[1]Burgiss_Return!$B:$P,MATCH(B$2,[1]Burgiss_Return!$B$5:$P$5,0),0) -> 0.0159 | C106: =VLOOKUP($A106,[1]Burgiss_Return!$B:$P,MATCH(C$2,[1]Burgiss_Return!$B$5:$P$5,0),0) -> 0.0742 | D106: =VLOOKUP($A106,[1]Burgiss_Return!$B:$P,MATCH(D$2,[1]Burgiss_Return!$B$5:$P$5,0),0) -> 0.0742 | E106: =VLOOKUP($A106,[1]Burgiss_Return!$B:$P,MATCH(E$2,[1]Burgiss_Return!$B$5:$P$5,0),0) -> 0.0255 | F106: =VLOOKUP($A106,[1]Burgiss_Return!$B:$P,MATCH(F$2,[1]Burgiss_Return!$B$5:$P$5,0),0) -> 0.0396 | G106: =VLOOKUP($A106,[1]Burgiss_Return!$B:$P,MATCH(G$2,[1]Burgiss_Return!$B$5:$P$5,0),0) -> 0.0255 | H106: =VLOOKUP($A106,[1]Burgiss_Return!$B:$P,MATCH(H$2,[1]Burgiss_Return!$B$5:$P$5,0),0) -> 0.0156 | I106: =VLOOKUP($A106,[1]Burgiss_Return!$B:$P,MATCH(I$2,[1]Burgiss_Return!$B$5:$P$5,0),0) -> 0.0203 | J106: =VLOOKUP($A106,[1]Burgiss_Return!$B:$P,MATCH(J$2,[1]Burgiss_Return!$B$5:$P$5,0),0) -> 0.0363 | K106: 0.028056075 | M106: =VLOOKUP($A106,[1]Burgiss_Return!$B:$P,MATCH(M$2,[1]Burgiss_Return!$B$5:$P$5,0),0) -> -0.0037 | Q106: 0.043119182 | R106: =VLOOKUP($A106,[1]Burgiss_Return!$B:$P,MATCH(R$2,[1]Burgiss_Return!$B$5:$P$5,0),0) -> 0.0078 | S106: =VLOOKUP($A106,[1]Burgiss_Return!$B:$P,MATCH(S$2,[1]Burgiss_Return!$B$5:$P$5,0),0) -> 0.0078 | T106: =VLOOKUP($A106,[1]Burgiss_Return!$B:$P,MATCH(T$2,[1]Burgiss_Return!$B$5:$P$5,0),0) -> 0.0078 | U106: =VLOOKUP($A106,[1]Burgiss_Return!$B:$P,MATCH(U$2,[1]Burgiss_Return!$B$5:$P$5,0),0) -> 0.0078 | V106: 0.030681805
A107: 46022 | B107: =VLOOKUP($A107,[1]Burgiss_Return!$B:$P,MATCH(B$2,[1]Burgiss_Return!$B$5:$P$5,0),0) -> 0.0194 | C107: =VLOOKUP($A107,[1]Burgiss_Return!$B:$P,MATCH(C$2,[1]Burgiss_Return!$B$5:$P$5,0),0) -> 0.0889 | D107: =VLOOKUP($A107,[1]Burgiss_Return!$B:$P,MATCH(D$2,[1]Burgiss_Return!$B$5:$P$5,0),0) -> 0.0889 | E107: =VLOOKUP($A107,[1]Burgiss_Return!$B:$P,MATCH(E$2,[1]Burgiss_Return!$B$5:$P$5,0),0) -> 0.0132 | F107: =VLOOKUP($A107,[1]Burgiss_Return!$B:$P,MATCH(F$2,[1]Burgiss_Return!$B$5:$P$5,0),0) -> 0.0359 | G107: =VLOOKUP($A107,[1]Burgiss_Return!$B:$P,MATCH(G$2,[1]Burgiss_Return!$B$5:$P$5,0),0) -> 0.0132 | H107: =VLOOKUP($A107,[1]Burgiss_Return!$B:$P,MATCH(H$2,[1]Burgiss_Return!$B$5:$P$5,0),0) -> 0.0095 | I107: =VLOOKUP($A107,[1]Burgiss_Return!$B:$P,MATCH(I$2,[1]Burgiss_Return!$B$5:$P$5,0),0) -> 0.0147 | J107: =VLOOKUP($A107,[1]Burgiss_Return!$B:$P,MATCH(J$2,[1]Burgiss_Return!$B$5:$P$5,0),0) -> 0.0278 | K107: 0.023419321 | M107: =VLOOKUP($A107,[1]Burgiss_Return!$B:$P,MATCH(M$2,[1]Burgiss_Return!$B$5:$P$5,0),0) -> 0.0008 | Q107: -0.0050081044 | R107: =VLOOKUP($A107,[1]Burgiss_Return!$B:$P,MATCH(R$2,[1]Burgiss_Return!$B$5:$P$5,0),0) -> 0.017 | S107: =VLOOKUP($A107,[1]Burgiss_Return!$B:$P,MATCH(S$2,[1]Burgiss_Return!$B$5:$P$5,0),0) -> 0.017 | T107: =VLOOKUP($A107,[1]Burgiss_Return!$B:$P,MATCH(T$2,[1]Burgiss_Return!$B$5:$P$5,0),0) -> 0.017 | U107: =VLOOKUP($A107,[1]Burgiss_Return!$B:$P,MATCH(U$2,[1]Burgiss_Return!$B$5:$P$5,0),0) -> 0.017 | V107: 0.0085031105
A108: 46112 | B108: =VLOOKUP($A108,[1]Burgiss_Return!$B:$P,MATCH(B$2,[1]Burgiss_Return!$B$5:$P$5,0),0) -> -0.0092 | C108: =VLOOKUP($A108,[1]Burgiss_Return!$B:$P,MATCH(C$2,[1]Burgiss_Return!$B$5:$P$5,0),0) -> 0.0381 | D108: =VLOOKUP($A108,[1]Burgiss_Return!$B:$P,MATCH(D$2,[1]Burgiss_Return!$B$5:$P$5,0),0) -> 0.0381 | E108: =VLOOKUP($A108,[1]Burgiss_Return!$B:$P,MATCH(E$2,[1]Burgiss_Return!$B$5:$P$5,0),0) -> -0.0058 | F108: =VLOOKUP($A108,[1]Burgiss_Return!$B:$P,MATCH(F$2,[1]Burgiss_Return!$B$5:$P$5,0),0) -> 0.0054 | G108: =VLOOKUP($A108,[1]Burgiss_Return!$B:$P,MATCH(G$2,[1]Burgiss_Return!$B$5:$P$5,0),0) -> -0.0058 | H108: =VLOOKUP($A108,[1]Burgiss_Return!$B:$P,MATCH(H$2,[1]Burgiss_Return!$B$5:$P$5,0),0) -> -0.0016 | I108: =VLOOKUP($A108,[1]Burgiss_Return!$B:$P,MATCH(I$2,[1]Burgiss_Return!$B$5:$P$5,0),0) -> 0.0114 | J108: =VLOOKUP($A108,[1]Burgiss_Return!$B:$P,MATCH(J$2,[1]Burgiss_Return!$B$5:$P$5,0),0) -> 0.0186 | K108: 0.011462836 | M108: =VLOOKUP($A108,[1]Burgiss_Return!$B:$P,MATCH(M$2,[1]Burgiss_Return!$B$5:$P$5,0),0) -> -0.0053 | Q108: 0.013008541 | R108: =VLOOKUP($A108,[1]Burgiss_Return!$B:$P,MATCH(R$2,[1]Burgiss_Return!$B$5:$P$5,0),0) -> -0.0069 | S108: =VLOOKUP($A108,[1]Burgiss_Return!$B:$P,MATCH(S$2,[1]Burgiss_Return!$B$5:$P$5,0),0) -> -0.0069 | T108: =VLOOKUP($A108,[1]Burgiss_Return!$B:$P,MATCH(T$2,[1]Burgiss_Return!$B$5:$P$5,0),0) -> -0.0069 | U108: =VLOOKUP($A108,[1]Burgiss_Return!$B:$P,MATCH(U$2,[1]Burgiss_Return!$B$5:$P$5,0),0) -> -0.0069 | V108: -0.0037779273

Sheet Main
A1: Date | B1: Buyout | C1: Growth | D1: Venture Capital | E1: Fund of Fund | F1: Long-term Core | G1: GP-Stake / Continuation Vehicle | H1: Senior Credit | I1: Junior Credit | J1: 국내 사모투자 | K1: Hedge Fund | L1: Core RE Equity | M1: Non-Core RE Equity | N1: 국내 부동산 | O1: Core RE Debt | P1: Non-Core RE Debt | Q1: Listed RE | R1: Core 국내 인프라 | S1: Non-Core 국내 인프라 | T1: Core 해외 인프라 | U1: Non-Core 해외 인프라 | V1: Super-Core Infrastructure
A2: 36616 | B2: =IF(VLOOKUP($A2,값!$A:$W,MATCH(Main!B$1,값!$2:$2,0),0)="",NA(),VLOOKUP($A2,값!$A:$W,MATCH(Main!B$1,값!$2:$2,0),0)) -> 0.1103 | C2: =IF(VLOOKUP($A2,값!$A:$W,MATCH(Main!C$1,값!$2:$2,0),0)="",NA(),VLOOKUP($A2,값!$A:$W,MATCH(Main!C$1,값!$2:$2,0),0)) -> 0.1533 | D2: =IF(VLOOKUP($A2,값!$A:$W,MATCH(Main!D$1,값!$2:$2,0),0)="",NA(),VLOOKUP($A2,값!$A:$W,MATCH(Main!D$1,값!$2:$2,0),0)) -> 0.1533 | E2: =IF(VLOOKUP($A2,값!$A:$W,MATCH(Main!E$1,값!$2:$2,0),0)="",NA(),VLOOKUP($A2,값!$A:$W,MATCH(Main!E$1,값!$2:$2,0),0)) -> #N/A | F2: =IF(VLOOKUP($A2,값!$A:$W,MATCH(Main!F$1,값!$2:$2,0),0)="",NA(),VLOOKUP($A2,값!$A:$W,MATCH(Main!F$1,값!$2:$2,0),0)) -> 0.0053 | G2: =IF(VLOOKUP($A2,값!$A:$W,MATCH(Main!G$1,값!$2:$2,0),0)="",NA(),VLOOKUP($A2,값!$A:$W,MATCH(Main!G$1,값!$2:$2,0),0)) -> #N/A | H2: =IF(VLOOKUP($A2,값!$A:$W,MATCH(Main!H$1,값!$2:$2,0),0)="",NA(),VLOOKUP($A2,값!$A:$W,MATCH(Main!H$1,값!$2:$2,0),0)) -> #N/A | I2: =IF(VLOOKUP($A2,값!$A:$W,MATCH(Main!I$1,값!$2:$2,0),0)="",NA(),VLOOKUP($A2,값!$A:$W,MATCH(Main!I$1,값!$2:$2,0),0)) -> 0.0114 | ... V2: =IF(VLOOKUP($A2,값!$A:$W,MATCH(Main!V$1,값!$2:$2,0),0)="",NA(),VLOOKUP($A2,값!$A:$W,MATCH(Main!V$1,값!$2:$2,0),0)) -> #N/A
A3: 36707 | B3: =IF(VLOOKUP($A3,값!$A:$W,MATCH(Main!B$1,값!$2:$2,0),0)="",NA(),VLOOKUP($A3,값!$A:$W,MATCH(Main!B$1,값!$2:$2,0),0)) -> -0.0009 | C3: =IF(VLOOKUP($A3,값!$A:$W,MATCH(Main!C$1,값!$2:$2,0),0)="",NA(),VLOOKUP($A3,값!$A:$W,MATCH(Main!C$1,값!$2:$2,0),0)) -> 0.0751 | D3: =IF(VLOOKUP($A3,값!$A:$W,MATCH(Main!D$1,값!$2:$2,0),0)="",NA(),VLOOKUP($A3,값!$A:$W,MATCH(Main!D$1,값!$2:$2,0),0)) -> 0.0751 | E3: =IF(VLOOKUP($A3,값!$A:$W,MATCH(Main!E$1,값!$2:$2,0),0)="",NA(),VLOOKUP($A3,값!$A:$W,MATCH(Main!E$1,값!$2:$2,0),0)) -> #N/A | F3: =IF(VLOOKUP($A3,값!$A:$W,MATCH(Main!F$1,값!$2:$2,0),0)="",NA(),VLOOKUP($A3,값!$A:$W,MATCH(Main!F$1,값!$2:$2,0),0)) -> 0.0363 | G3: =IF(VLOOKUP($A3,값!$A:$W,MATCH(Main!G$1,값!$2:$2,0),0)="",NA(),VLOOKUP($A3,값!$A:$W,MATCH(Main!G$1,값!$2:$2,0),0)) -> #N/A | H3: =IF(VLOOKUP($A3,값!$A:$W,MATCH(Main!H$1,값!$2:$2,0),0)="",NA(),VLOOKUP($A3,값!$A:$W,MATCH(Main!H$1,값!$2:$2,0),0)) -> #N/A | I3: =IF(VLOOKUP($A3,값!$A:$W,MATCH(Main!I$1,값!$2:$2,0),0)="",NA(),VLOOKUP($A3,값!$A:$W,MATCH(Main!I$1,값!$2:$2,0),0)) -> 0.0159 | ... V3: =IF(VLOOKUP($A3,값!$A:$W,MATCH(Main!V$1,값!$2:$2,0),0)="",NA(),VLOOKUP($A3,값!$A:$W,MATCH(Main!V$1,값!$2:$2,0),0)) -> #N/A
A4: 36799 | B4: =IF(VLOOKUP($A4,값!$A:$W,MATCH(Main!B$1,값!$2:$2,0),0)="",NA(),VLOOKUP($A4,값!$A:$W,MATCH(Main!B$1,값!$2:$2,0),0)) -> -0.0295 | C4: =IF(VLOOKUP($A4,값!$A:$W,MATCH(Main!C$1,값!$2:$2,0),0)="",NA(),VLOOKUP($A4,값!$A:$W,MATCH(Main!C$1,값!$2:$2,0),0)) -> 0.1497 | D4: =IF(VLOOKUP($A4,값!$A:$W,MATCH(Main!D$1,값!$2:$2,0),0)="",NA(),VLOOKUP($A4,값!$A:$W,MATCH(Main!D$1,값!$2:$2,0),0)) -> 0.1497 | E4: =IF(VLOOKUP($A4,값!$A:$W,MATCH(Main!E$1,값!$2:$2,0),0)="",NA(),VLOOKUP($A4,값!$A:$W,MATCH(Main!E$1,값!$2:$2,0),0)) -> #N/A | F4: =IF(VLOOKUP($A4,값!$A:$W,MATCH(Main!F$1,값!$2:$2,0),0)="",NA(),VLOOKUP($A4,값!$A:$W,MATCH(Main!F$1,값!$2:$2,0),0)) -> 0.0089 | G4: =IF(VLOOKUP($A4,값!$A:$W,MATCH(Main!G$1,값!$2:$2,0),0)="",NA(),VLOOKUP($A4,값!$A:$W,MATCH(Main!G$1,값!$2:$2,0),0)) -> #N/A | H4: =IF(VLOOKUP($A4,값!$A:$W,MATCH(Main!H$1,값!$2:$2,0),0)="",NA(),VLOOKUP($A4,값!$A:$W,MATCH(Main!H$1,값!$2:$2,0),0)) -> #N/A | I4: =IF(VLOOKUP($A4,값!$A:$W,MATCH(Main!I$1,값!$2:$2,0),0)="",NA(),VLOOKUP($A4,값!$A:$W,MATCH(Main!I$1,값!$2:$2,0),0)) -> 0.0368 | ... V4: =IF(VLOOKUP($A4,값!$A:$W,MATCH(Main!V$1,값!$2:$2,0),0)="",NA(),VLOOKUP($A4,값!$A:$W,MATCH(Main!V$1,값!$2:$2,0),0)) -> #N/A
A5: 36891 | B5: =IF(VLOOKUP($A5,값!$A:$W,MATCH(Main!B$1,값!$2:$2,0),0)="",NA(),VLOOKUP($A5,값!$A:$W,MATCH(Main!B$1,값!$2:$2,0),0)) -> -0.0306 | C5: =IF(VLOOKUP($A5,값!$A:$W,MATCH(Main!C$1,값!$2:$2,0),0)="",NA(),VLOOKUP($A5,값!$A:$W,MATCH(Main!C$1,값!$2:$2,0),0)) -> -0.1013 | D5: =IF(VLOOKUP($A5,값!$A:$W,MATCH(Main!D$1,값!$2:$2,0),0)="",NA(),VLOOKUP($A5,값!$A:$W,MATCH(Main!D$1,값!$2:$2,0),0)) -> -0.1013 | E5: =IF(VLOOKUP($A5,값!$A:$W,MATCH(Main!E$1,값!$2:$2,0),0)="",NA(),VLOOKUP($A5,값!$A:$W,MATCH(Main!E$1,값!$2:$2,0),0)) -> #N/A | F5: =IF(VLOOKUP($A5,값!$A:$W,MATCH(Main!F$1,값!$2:$2,0),0)="",NA(),VLOOKUP($A5,값!$A:$W,MATCH(Main!F$1,값!$2:$2,0),0)) -> -0.0575 | G5: =IF(VLOOKUP($A5,값!$A:$W,MATCH(Main!G$1,값!$2:$2,0),0)="",NA(),VLOOKUP($A5,값!$A:$W,MATCH(Main!G$1,값!$2:$2,0),0)) -> #N/A | H5: =IF(VLOOKUP($A5,값!$A:$W,MATCH(Main!H$1,값!$2:$2,0),0)="",NA(),VLOOKUP($A5,값!$A:$W,MATCH(Main!H$1,값!$2:$2,0),0)) -> #N/A | I5: =IF(VLOOKUP($A5,값!$A:$W,MATCH(Main!I$1,값!$2:$2,0),0)="",NA(),VLOOKUP($A5,값!$A:$W,MATCH(Main!I$1,값!$2:$2,0),0)) -> -0.0183 | ... V5: =IF(VLOOKUP($A5,값!$A:$W,MATCH(Main!V$1,값!$2:$2,0),0)="",NA(),VLOOKUP($A5,값!$A:$W,MATCH(Main!V$1,값!$2:$2,0),0)) -> #N/A
A6: 36981 | B6: =IF(VLOOKUP($A6,값!$A:$W,MATCH(Main!B$1,값!$2:$2,0),0)="",NA(),VLOOKUP($A6,값!$A:$W,MATCH(Main!B$1,값!$2:$2,0),0)) -> -0.0635 | C6: =IF(VLOOKUP($A6,값!$A:$W,MATCH(Main!C$1,값!$2:$2,0),0)="",NA(),VLOOKUP($A6,값!$A:$W,MATCH(Main!C$1,값!$2:$2,0),0)) -> -0.0899 | D6: =IF(VLOOKUP($A6,값!$A:$W,MATCH(Main!D$1,값!$2:$2,0),0)="",NA(),VLOOKUP($A6,값!$A:$W,MATCH(Main!D$1,값!$2:$2,0),0)) -> -0.0899 | E6: =IF(VLOOKUP($A6,값!$A:$W,MATCH(Main!E$1,값!$2:$2,0),0)="",NA(),VLOOKUP($A6,값!$A:$W,MATCH(Main!E$1,값!$2:$2,0),0)) -> #N/A | F6: =IF(VLOOKUP($A6,값!$A:$W,MATCH(Main!F$1,값!$2:$2,0),0)="",NA(),VLOOKUP($A6,값!$A:$W,MATCH(Main!F$1,값!$2:$2,0),0)) -> -0.0119 | G6: =IF(VLOOKUP($A6,값!$A:$W,MATCH(Main!G$1,값!$2:$2,0),0)="",NA(),VLOOKUP($A6,값!$A:$W,MATCH(Main!G$1,값!$2:$2,0),0)) -> #N/A | H6: =IF(VLOOKUP($A6,값!$A:$W,MATCH(Main!H$1,값!$2:$2,0),0)="",NA(),VLOOKUP($A6,값!$A:$W,MATCH(Main!H$1,값!$2:$2,0),0)) -> #N/A | I6: =IF(VLOOKUP($A6,값!$A:$W,MATCH(Main!I$1,값!$2:$2,0),0)="",NA(),VLOOKUP($A6,값!$A:$W,MATCH(Main!I$1,값!$2:$2,0),0)) -> 0.0647 | ... V6: =IF(VLOOKUP($A6,값!$A:$W,MATCH(Main!V$1,값!$2:$2,0),0)="",NA(),VLOOKUP($A6,값!$A:$W,MATCH(Main!V$1,값!$2:$2,0),0)) -> #N/A
A7: 37072 | B7: =IF(VLOOKUP($A7,값!$A:$W,MATCH(Main!B$1,값!$2:$2,0),0)="",NA(),VLOOKUP($A7,값!$A:$W,MATCH(Main!B$1,값!$2:$2,0),0)) -> 0.0238 | C7: =IF(VLOOKUP($A7,값!$A:$W,MATCH(Main!C$1,값!$2:$2,0),0)="",NA(),VLOOKUP($A7,값!$A:$W,MATCH(Main!C$1,값!$2:$2,0),0)) -> -0.0746 | D7: =IF(VLOOKUP($A7,값!$A:$W,MATCH(Main!D$1,값!$2:$2,0),0)="",NA(),VLOOKUP($A7,값!$A:$W,MATCH(Main!D$1,값!$2:$2,0),0)) -> -0.0746 | E7: =IF(VLOOKUP($A7,값!$A:$W,MATCH(Main!E$1,값!$2:$2,0),0)="",NA(),VLOOKUP($A7,값!$A:$W,MATCH(Main!E$1,값!$2:$2,0),0)) -> #N/A | F7: =IF(VLOOKUP($A7,값!$A:$W,MATCH(Main!F$1,값!$2:$2,0),0)="",NA(),VLOOKUP($A7,값!$A:$W,MATCH(Main!F$1,값!$2:$2,0),0)) -> -0.0608 | G7: =IF(VLOOKUP($A7,값!$A:$W,MATCH(Main!G$1,값!$2:$2,0),0)="",NA(),VLOOKUP($A7,값!$A:$W,MATCH(Main!G$1,값!$2:$2,0),0)) -> #N/A | H7: =IF(VLOOKUP($A7,값!$A:$W,MATCH(Main!H$1,값!$2:$2,0),0)="",NA(),VLOOKUP($A7,값!$A:$W,MATCH(Main!H$1,값!$2:$2,0),0)) -> #N/A | I7: =IF(VLOOKUP($A7,값!$A:$W,MATCH(Main!I$1,값!$2:$2,0),0)="",NA(),VLOOKUP($A7,값!$A:$W,MATCH(Main!I$1,값!$2:$2,0),0)) -> 0.029 | ... V7: =IF(VLOOKUP($A7,값!$A:$W,MATCH(Main!V$1,값!$2:$2,0),0)="",NA(),VLOOKUP($A7,값!$A:$W,MATCH(Main!V$1,값!$2:$2,0),0)) -> #N/A
A8: 37164 | B8: =IF(VLOOKUP($A8,값!$A:$W,MATCH(Main!B$1,값!$2:$2,0),0)="",NA(),VLOOKUP($A8,값!$A:$W,MATCH(Main!B$1,값!$2:$2,0),0)) -> -0.0809 | C8: =IF(VLOOKUP($A8,값!$A:$W,MATCH(Main!C$1,값!$2:$2,0),0)="",NA(),VLOOKUP($A8,값!$A:$W,MATCH(Main!C$1,값!$2:$2,0),0)) -> -0.1505 | D8: =IF(VLOOKUP($A8,값!$A:$W,MATCH(Main!D$1,값!$2:$2,0),0)="",NA(),VLOOKUP($A8,값!$A:$W,MATCH(Main!D$1,값!$2:$2,0),0)) -> -0.1505 | E8: =IF(VLOOKUP($A8,값!$A:$W,MATCH(Main!E$1,값!$2:$2,0),0)="",NA(),VLOOKUP($A8,값!$A:$W,MATCH(Main!E$1,값!$2:$2,0),0)) -> #N/A | F8: =IF(VLOOKUP($A8,값!$A:$W,MATCH(Main!F$1,값!$2:$2,0),0)="",NA(),VLOOKUP($A8,값!$A:$W,MATCH(Main!F$1,값!$2:$2,0),0)) -> -0.0545 | G8: =IF(VLOOKUP($A8,값!$A:$W,MATCH(Main!G$1,값!$2:$2,0),0)="",NA(),VLOOKUP($A8,값!$A:$W,MATCH(Main!G$1,값!$2:$2,0),0)) -> #N/A | H8: =IF(VLOOKUP($A8,값!$A:$W,MATCH(Main!H$1,값!$2:$2,0),0)="",NA(),VLOOKUP($A8,값!$A:$W,MATCH(Main!H$1,값!$2:$2,0),0)) -> #N/A | I8: =IF(VLOOKUP($A8,값!$A:$W,MATCH(Main!I$1,값!$2:$2,0),0)="",NA(),VLOOKUP($A8,값!$A:$W,MATCH(Main!I$1,값!$2:$2,0),0)) -> 0.0149 | ... V8: =IF(VLOOKUP($A8,값!$A:$W,MATCH(Main!V$1,값!$2:$2,0),0)="",NA(),VLOOKUP($A8,값!$A:$W,MATCH(Main!V$1,값!$2:$2,0),0)) -> #N/A
A9: 37256 | B9: =IF(VLOOKUP($A9,값!$A:$W,MATCH(Main!B$1,값!$2:$2,0),0)="",NA(),VLOOKUP($A9,값!$A:$W,MATCH(Main!B$1,값!$2:$2,0),0)) -> -0.0011 | C9: =IF(VLOOKUP($A9,값!$A:$W,MATCH(Main!C$1,값!$2:$2,0),0)="",NA(),VLOOKUP($A9,값!$A:$W,MATCH(Main!C$1,값!$2:$2,0),0)) -> -0.0779 | D9: =IF(VLOOKUP($A9,값!$A:$W,MATCH(Main!D$1,값!$2:$2,0),0)="",NA(),VLOOKUP($A9,값!$A:$W,MATCH(Main!D$1,값!$2:$2,0),0)) -> -0.0779 | E9: =IF(VLOOKUP($A9,값!$A:$W,MATCH(Main!E$1,값!$2:$2,0),0)="",NA(),VLOOKUP($A9,값!$A:$W,MATCH(Main!E$1,값!$2:$2,0),0)) -> #N/A | F9: =IF(VLOOKUP($A9,값!$A:$W,MATCH(Main!F$1,값!$2:$2,0),0)="",NA(),VLOOKUP($A9,값!$A:$W,MATCH(Main!F$1,값!$2:$2,0),0)) -> -0.0812 | G9: =IF(VLOOKUP($A9,값!$A:$W,MATCH(Main!G$1,값!$2:$2,0),0)="",NA(),VLOOKUP($A9,값!$A:$W,MATCH(Main!G$1,값!$2:$2,0),0)) -> #N/A | H9: =IF(VLOOKUP($A9,값!$A:$W,MATCH(Main!H$1,값!$2:$2,0),0)="",NA(),VLOOKUP($A9,값!$A:$W,MATCH(Main!H$1,값!$2:$2,0),0)) -> #N/A | I9: =IF(VLOOKUP($A9,값!$A:$W,MATCH(Main!I$1,값!$2:$2,0),0)="",NA(),VLOOKUP($A9,값!$A:$W,MATCH(Main!I$1,값!$2:$2,0),0)) -> 0.021 | ... V9: =IF(VLOOKUP($A9,값!$A:$W,MATCH(Main!V$1,값!$2:$2,0),0)="",NA(),VLOOKUP($A9,값!$A:$W,MATCH(Main!V$1,값!$2:$2,0),0)) -> #N/A
A10: 37346 | B10: =IF(VLOOKUP($A10,값!$A:$W,MATCH(Main!B$1,값!$2:$2,0),0)="",NA(),VLOOKUP($A10,값!$A:$W,MATCH(Main!B$1,값!$2:$2,0),0)) -> -0.0023 | C10: =IF(VLOOKUP($A10,값!$A:$W,MATCH(Main!C$1,값!$2:$2,0),0)="",NA(),VLOOKUP($A10,값!$A:$W,MATCH(Main!C$1,값!$2:$2,0),0)) -> -0.0948 | D10: =IF(VLOOKUP($A10,값!$A:$W,MATCH(Main!D$1,값!$2:$2,0),0)="",NA(),VLOOKUP($A10,값!$A:$W,MATCH(Main!D$1,값!$2:$2,0),0)) -> -0.0948 | E10: =IF(VLOOKUP($A10,값!$A:$W,MATCH(Main!E$1,값!$2:$2,0),0)="",NA(),VLOOKUP($A10,값!$A:$W,MATCH(Main!E$1,값!$2:$2,0),0)) -> 0.0327 | F10: =IF(VLOOKUP($A10,값!$A:$W,MATCH(Main!F$1,값!$2:$2,0),0)="",NA(),VLOOKUP($A10,값!$A:$W,MATCH(Main!F$1,값!$2:$2,0),0)) -> -0.025 | G10: =IF(VLOOKUP($A10,값!$A:$W,MATCH(Main!G$1,값!$2:$2,0),0)="",NA(),VLOOKUP($A10,값!$A:$W,MATCH(Main!G$1,값!$2:$2,0),0)) -> 0.0327 | H10: =IF(VLOOKUP($A10,값!$A:$W,MATCH(Main!H$1,값!$2:$2,0),0)="",NA(),VLOOKUP($A10,값!$A:$W,MATCH(Main!H$1,값!$2:$2,0),0)) -> #N/A | I10: =IF(VLOOKUP($A10,값!$A:$W,MATCH(Main!I$1,값!$2:$2,0),0)="",NA(),VLOOKUP($A10,값!$A:$W,MATCH(Main!I$1,값!$2:$2,0),0)) -> 0.0377 | ... V10: =IF(VLOOKUP($A10,값!$A:$W,MATCH(Main!V$1,값!$2:$2,0),0)="",NA(),VLOOKUP($A10,값!$A:$W,MATCH(Main!V$1,값!$2:$2,0),0)) -> #N/A
A11: 37437 | B11: =IF(VLOOKUP($A11,값!$A:$W,MATCH(Main!B$1,값!$2:$2,0),0)="",NA(),VLOOKUP($A11,값!$A:$W,MATCH(Main!B$1,값!$2:$2,0),0)) -> -0.0135 | C11: =IF(VLOOKUP($A11,값!$A:$W,MATCH(Main!C$1,값!$2:$2,0),0)="",NA(),VLOOKUP($A11,값!$A:$W,MATCH(Main!C$1,값!$2:$2,0),0)) -> -0.1303 | D11: =IF(VLOOKUP($A11,값!$A:$W,MATCH(Main!D$1,값!$2:$2,0),0)="",NA(),VLOOKUP($A11,값!$A:$W,MATCH(Main!D$1,값!$2:$2,0),0)) -> -0.1303 | E11: =IF(VLOOKUP($A11,값!$A:$W,MATCH(Main!E$1,값!$2:$2,0),0)="",NA(),VLOOKUP($A11,값!$A:$W,MATCH(Main!E$1,값!$2:$2,0),0)) -> 0.0174 | F11: =IF(VLOOKUP($A11,값!$A:$W,MATCH(Main!F$1,값!$2:$2,0),0)="",NA(),VLOOKUP($A11,값!$A:$W,MATCH(Main!F$1,값!$2:$2,0),0)) -> -0.0711 | G11: =IF(VLOOKUP($A11,값!$A:$W,MATCH(Main!G$1,값!$2:$2,0),0)="",NA(),VLOOKUP($A11,값!$A:$W,MATCH(Main!G$1,값!$2:$2,0),0)) -> 0.0174 | H11: =IF(VLOOKUP($A11,값!$A:$W,MATCH(Main!H$1,값!$2:$2,0),0)="",NA(),VLOOKUP($A11,값!$A:$W,MATCH(Main!H$1,값!$2:$2,0),0)) -> #N/A | I11: =IF(VLOOKUP($A11,값!$A:$W,MATCH(Main!I$1,값!$2:$2,0),0)="",NA(),VLOOKUP($A11,값!$A:$W,MATCH(Main!I$1,값!$2:$2,0),0)) -> -0.001 | ... V11: =IF(VLOOKUP($A11,값!$A:$W,MATCH(Main!V$1,값!$2:$2,0),0)="",NA(),VLOOKUP($A11,값!$A:$W,MATCH(Main!V$1,값!$2:$2,0),0)) -> #N/A
A12: 37529 | B12: =IF(VLOOKUP($A12,값!$A:$W,MATCH(Main!B$1,값!$2:$2,0),0)="",NA(),VLOOKUP($A12,값!$A:$W,MATCH(Main!B$1,값!$2:$2,0),0)) -> -0.0398 | C12: =IF(VLOOKUP($A12,값!$A:$W,MATCH(Main!C$1,값!$2:$2,0),0)="",NA(),VLOOKUP($A12,값!$A:$W,MATCH(Main!C$1,값!$2:$2,0),0)) -> -0.0991 | D12: =IF(VLOOKUP($A12,값!$A:$W,MATCH(Main!D$1,값!$2:$2,0),0)="",NA(),VLOOKUP($A12,값!$A:$W,MATCH(Main!D$1,값!$2:$2,0),0)) -> -0.0991 | E12: =IF(VLOOKUP($A12,값!$A:$W,MATCH(Main!E$1,값!$2:$2,0),0)="",NA(),VLOOKUP($A12,값!$A:$W,MATCH(Main!E$1,값!$2:$2,0),0)) -> -0.0334 | F12: =IF(VLOOKUP($A12,값!$A:$W,MATCH(Main!F$1,값!$2:$2,0),0)="",NA(),VLOOKUP($A12,값!$A:$W,MATCH(Main!F$1,값!$2:$2,0),0)) -> -0.0593 | G12: =IF(VLOOKUP($A12,값!$A:$W,MATCH(Main!G$1,값!$2:$2,0),0)="",NA(),VLOOKUP($A12,값!$A:$W,MATCH(Main!G$1,값!$2:$2,0),0)) -> -0.0334 | H12: =IF(VLOOKUP($A12,값!$A:$W,MATCH(Main!H$1,값!$2:$2,0),0)="",NA(),VLOOKUP($A12,값!$A:$W,MATCH(Main!H$1,값!$2:$2,0),0)) -> #N/A | I12: =IF(VLOOKUP($A12,값!$A:$W,MATCH(Main!I$1,값!$2:$2,0),0)="",NA(),VLOOKUP($A12,값!$A:$W,MATCH(Main!I$1,값!$2:$2,0),0)) -> -0.0519 | ... V12: =IF(VLOOKUP($A12,값!$A:$W,MATCH(Main!V$1,값!$2:$2,0),0)="",NA(),VLOOKUP($A12,값!$A:$W,MATCH(Main!V$1,값!$2:$2,0),0)) -> #N/A
A13: 37621 | B13: =IF(VLOOKUP($A13,값!$A:$W,MATCH(Main!B$1,값!$2:$2,0),0)="",NA(),VLOOKUP($A13,값!$A:$W,MATCH(Main!B$1,값!$2:$2,0),0)) -> 0.0208 | C13: =IF(VLOOKUP($A13,값!$A:$W,MATCH(Main!C$1,값!$2:$2,0),0)="",NA(),VLOOKUP($A13,값!$A:$W,MATCH(Main!C$1,값!$2:$2,0),0)) -> -0.1076 | D13: =IF(VLOOKUP($A13,값!$A:$W,MATCH(Main!D$1,값!$2:$2,0),0)="",NA(),VLOOKUP($A13,값!$A:$W,MATCH(Main!D$1,값!$2:$2,0),0)) -> -0.1076 | E13: =IF(VLOOKUP($A13,값!$A:$W,MATCH(Main!E$1,값!$2:$2,0),0)="",NA(),VLOOKUP($A13,값!$A:$W,MATCH(Main!E$1,값!$2:$2,0),0)) -> -0.0336 | F13: =IF(VLOOKUP($A13,값!$A:$W,MATCH(Main!F$1,값!$2:$2,0),0)="",NA(),VLOOKUP($A13,값!$A:$W,MATCH(Main!F$1,값!$2:$2,0),0)) -> -0.0763 | G13: =IF(VLOOKUP($A13,값!$A:$W,MATCH(Main!G$1,값!$2:$2,0),0)="",NA(),VLOOKUP($A13,값!$A:$W,MATCH(Main!G$1,값!$2:$2,0),0)) -> -0.0336 | H13: =IF(VLOOKUP($A13,값!$A:$W,MATCH(Main!H$1,값!$2:$2,0),0)="",NA(),VLOOKUP($A13,값!$A:$W,MATCH(Main!H$1,값!$2:$2,0),0)) -> #N/A | I13: =IF(VLOOKUP($A13,값!$A:$W,MATCH(Main!I$1,값!$2:$2,0),0)="",NA(),VLOOKUP($A13,값!$A:$W,MATCH(Main!I$1,값!$2:$2,0),0)) -> 0.0741 | ... V13: =IF(VLOOKUP($A13,값!$A:$W,MATCH(Main!V$1,값!$2:$2,0),0)="",NA(),VLOOKUP($A13,값!$A:$W,MATCH(Main!V$1,값!$2:$2,0),0)) -> #N/A
... A106: 46112 | B106: =IF(VLOOKUP($A106,값!$A:$W,MATCH(Main!B$1,값!$2:$2,0),0)="",NA(),VLOOKUP($A106,값!$A:$W,MATCH(Main!B$1,값!$2:$2,0),0)) -> -0.0092 | C106: =IF(VLOOKUP($A106,값!$A:$W,MATCH(Main!C$1,값!$2:$2,0),0)="",NA(),VLOOKUP($A106,값!$A:$W,MATCH(Main!C$1,값!$2:$2,0),0)) -> 0.0381 | D106: =IF(VLOOKUP($A106,값!$A:$W,MATCH(Main!D$1,값!$2:$2,0),0)="",NA(),VLOOKUP($A106,값!$A:$W,MATCH(Main!D$1,값!$2:$2,0),0)) -> 0.0381 | E106: =IF(VLOOKUP($A106,값!$A:$W,MATCH(Main!E$1,값!$2:$2,0),0)="",NA(),VLOOKUP($A106,값!$A:$W,MATCH(Main!E$1,값!$2:$2,0),0)) -> -0.0058 | F106: =IF(VLOOKUP($A106,값!$A:$W,MATCH(Main!F$1,값!$2:$2,0),0)="",NA(),VLOOKUP($A106,값!$A:$W,MATCH(Main!F$1,값!$2:$2,0),0)) -> 0.0054 | G106: =IF(VLOOKUP($A106,값!$A:$W,MATCH(Main!G$1,값!$2:$2,0),0)="",NA(),VLOOKUP($A106,값!$A:$W,MATCH(Main!G$1,값!$2:$2,0),0)) -> -0.0058 | H106: =IF(VLOOKUP($A106,값!$A:$W,MATCH(Main!H$1,값!$2:$2,0),0)="",NA(),VLOOKUP($A106,값!$A:$W,MATCH(Main!H$1,값!$2:$2,0),0)) -> -0.0016 | I106: =IF(VLOOKUP($A106,값!$A:$W,MATCH(Main!I$1,값!$2:$2,0),0)="",NA(),VLOOKUP($A106,값!$A:$W,MATCH(Main!I$1,값!$2:$2,0),0)) -> 0.0114 | ... V106: =IF(VLOOKUP($A106,값!$A:$W,MATCH(Main!V$1,값!$2:$2,0),0)="",NA(),VLOOKUP($A106,값!$A:$W,MATCH(Main!V$1,값!$2:$2,0),0)) -> -0.0037779273
